Workbook

Sheet Trade Database
A1: TRADE LIFECYCLE OPERATIONS COMMAND CENTER
A2: IronHub Capital | T+1 Settlement Desk | India Markets | Equities | Fixed Income | Derivatives | Commodities
A4: Trade ID | B4: Trade Date | C4: Settlement Date | D4: Asset Class | E4: Product | F4: ISIN | G4: Currency | H4: Quantity | I4: Price | J4: Trade Value | K4: Broker | L4: Counterparty | M4: Lifecycle Stage | N4: Trade Status | O4: Failure Type | P4: Aging Days | Q4: Severity Score | R4: Risk Score | S4: RAG Status | T4: Settlement Risk | U4: Priority Rank
A5: TRD-001 | B5: 45688 | C5: 45689 | D5: Equity | E5: Tata Consultancy Services | F5: INE467B01029 | G5: INR | H5: 200 | I5: 3749.1 | J5: =H5*I5 -> 749820 | K5: HDFC Securities | L5: Nuvama Wealth | M5: S7 Settlement | N5: Settled | P5: =Config!$B$1-B5 -> 493 | Q5: =IFERROR(INDEX('Failure Reference'!$C$4:$C$9,MATCH(O5,'Failure Reference'!$A$4:$A$9,0)),0) -> 0 | R5: =IF(N5="Settled",0,Q5+P5*0.5+IFERROR(INDEX(Config!$B$4:$B$7,MATCH(D5,Config!$A$4:$A$7,0)),1)+IF(C5-Config!$B$1<=1,5,0)) -> 0 | S5: =IF(R5=0,"Green",IF(R5<10,"Amber","Red")) -> Green | T5: =IF(N5="Settled","None",IF(C5-Config!$B$1<=0,"Overdue",IF(C5-Config!$B$1<=1,"Critical",IF(C5-Config!$B$1<=3,"High","Low")))) -> None | U5: =IF(R5=0,"",RANK(R5,$R$5:$R$104,0))
A6: TRD-002 | B6: 45716 | C6: 45717 | D6: Equity | E6: Axis Bank Ltd | F6: INE238A01034 | G6: INR | H6: 200 | I6: 931.7 | J6: =H6*I6 -> 186340 | K6: HDFC Securities | L6: Axis Securities | M6: S7 Settlement | N6: Settled | P6: =Config!$B$1-B6 -> 465 | Q6: =IFERROR(INDEX('Failure Reference'!$C$4:$C$9,MATCH(O6,'Failure Reference'!$A$4:$A$9,0)),0) -> 0 | R6: =IF(N6="Settled",0,Q6+P6*0.5+IFERROR(INDEX(Config!$B$4:$B$7,MATCH(D6,Config!$A$4:$A$7,0)),1)+IF(C6-Config!$B$1<=1,5,0)) -> 0 | S6: =IF(R6=0,"Green",IF(R6<10,"Amber","Red")) -> Green | T6: =IF(N6="Settled","None",IF(C6-Config!$B$1<=0,"Overdue",IF(C6-Config!$B$1<=1,"Critical",IF(C6-Config!$B$1<=3,"High","Low")))) -> None | U6: =IF(R6=0,"",RANK(R6,$R$5:$R$104,0))
A7: TRD-003 | B7: 45675 | C7: 45676 | D7: Fixed Income | E7: 7.18% GOI 2033 | F7: IN002023Y123 | G7: INR | H7: 5000 | I7: 99.51 | J7: =H7*I7 -> 497550 | K7: Kotak Securities | L7: Sharekhan | M7: S5 Matching | N7: Break | O7: Matching Break | P7: =Config!$B$1-B7 -> 506 | Q7: =IFERROR(INDEX('Failure Reference'!$C$4:$C$9,MATCH(O7,'Failure Reference'!$A$4:$A$9,0)),0) -> 8 | R7: =IF(N7="Settled",0,Q7+P7*0.5+IFERROR(INDEX(Config!$B$4:$B$7,MATCH(D7,Config!$A$4:$A$7,0)),1)+IF(C7-Config!$B$1<=1,5,0)) -> 267.5 | S7: =IF(R7=0,"Green",IF(R7<10,"Amber","Red")) -> Red | T7: =IF(N7="Settled","None",IF(C7-Config!$B$1<=0,"Overdue",IF(C7-Config!$B$1<=1,"Critical",IF(C7-Config!$B$1<=3,"High","Low")))) -> Overdue | U7: =IF(R7=0,"",RANK(R7,$R$5:$R$104,0)) -> 2
A8: TRD-004 | B8: 45829 | C8: 45830 | D8: Fixed Income | E8: T-Bill 91D | F8: IN002024T001 | G8: INR | H8: 2000 | I8: 99.66 | J8: =H8*I8 -> 199320 | K8: Nuvama Wealth | L8: IIFL Securities | M8: S7 Settlement | N8: Settled | P8: =Config!$B$1-B8 -> 352 | Q8: =IFERROR(INDEX('Failure Reference'!$C$4:$C$9,MATCH(O8,'Failure Reference'!$A$4:$A$9,0)),0) -> 0 | R8: =IF(N8="Settled",0,Q8+P8*0.5+IFERROR(INDEX(Config!$B$4:$B$7,MATCH(D8,Config!$A$4:$A$7,0)),1)+IF(C8-Config!$B$1<=1,5,0)) -> 0 | S8: =IF(R8=0,"Green",IF(R8<10,"Amber","Red")) -> Green | T8: =IF(N8="Settled","None",IF(C8-Config!$B$1<=0,"Overdue",IF(C8-Config!$B$1<=1,"Critical",IF(C8-Config!$B$1<=3,"High","Low")))) -> None | U8: =IF(R8=0,"",RANK(R8,$R$5:$R$104,0))
A9: TRD-005 | B9: 45720 | C9: 45721 | D9: Equity | E9: Asian Paints Ltd | F9: INE021A01026 | G9: INR | H9: 500 | I9: 2978.87 | J9: =H9*I9 -> 1489435 | K9: Kotak Securities | L9: ICICI Securities | M9: S7 Settlement | N9: Settled | P9: =Config!$B$1-B9 -> 461 | Q9: =IFERROR(INDEX('Failure Reference'!$C$4:$C$9,MATCH(O9,'Failure Reference'!$A$4:$A$9,0)),0) -> 0 | R9: =IF(N9="Settled",0,Q9+P9*0.5+IFERROR(INDEX(Config!$B$4:$B$7,MATCH(D9,Config!$A$4:$A$7,0)),1)+IF(C9-Config!$B$1<=1,5,0)) -> 0 | S9: =IF(R9=0,"Green",IF(R9<10,"Amber","Red")) -> Green | T9: =IF(N9="Settled","None",IF(C9-Config!$B$1<=0,"Overdue",IF(C9-Config!$B$1<=1,"Critical",IF(C9-Config!$B$1<=3,"High","Low")))) -> None | U9: =IF(R9=0,"",RANK(R9,$R$5:$R$104,0))
A10: TRD-006 | B10: 45682 | C10: 45683 | D10: Fixed Income | E10: Tata Steel Corp Bond | F10: INE081A08123 | G10: INR | H10: 10000 | I10: 101.7 | J10: =H10*I10 -> 1017000 | K10: Angel One | L10: JM Financial | M10: S7 Settlement | N10: Settled | P10: =Config!$B$1-B10 -> 499 | Q10: =IFERROR(INDEX('Failure Reference'!$C$4:$C$9,MATCH(O10,'Failure Reference'!$A$4:$A$9,0)),0) -> 0 | R10: =IF(N10="Settled",0,Q10+P10*0.5+IFERROR(INDEX(Config!$B$4:$B$7,MATCH(D10,Config!$A$4:$A$7,0)),1)+IF(C10-Config!$B$1<=1,5,0)) -> 0 | S10: =IF(R10=0,"Green",IF(R10<10,"Amber","Red")) -> Green | T10: =IF(N10="Settled","None",IF(C10-Config!$B$1<=0,"Overdue",IF(C10-Config!$B$1<=1,"Critical",IF(C10-Config!$B$1<=3,"High","Low")))) -> None | U10: =IF(R10=0,"",RANK(R10,$R$5:$R$104,0))
A11: TRD-007 | B11: 45671 | C11: 45672 | D11: Fixed Income | E11: Tata Steel Corp Bond | F11: INE081A08123 | G11: INR | H11: 1000 | I11: 100.5 | J11: =H11*I11 -> 100500 | K11: Sharekhan | L11: ICICI Securities | M11: S7 Settlement | N11: Settled | P11: =Config!$B$1-B11 -> 510 | Q11: =IFERROR(INDEX('Failure Reference'!$C$4:$C$9,MATCH(O11,'Failure Reference'!$A$4:$A$9,0)),0) -> 0 | R11: =IF(N11="Settled",0,Q11+P11*0.5+IFERROR(INDEX(Config!$B$4:$B$7,MATCH(D11,Config!$A$4:$A$7,0)),1)+IF(C11-Config!$B$1<=1,5,0)) -> 0 | S11: =IF(R11=0,"Green",IF(R11<10,"Amber","Red")) -> Green | T11: =IF(N11="Settled","None",IF(C11-Config!$B$1<=0,"Overdue",IF(C11-Config!$B$1<=1,"Critical",IF(C11-Config!$B$1<=3,"High","Low")))) -> None | U11: =IF(R11=0,"",RANK(R11,$R$5:$R$104,0))
A12: TRD-008 | B12: 45721 | C12: 45722 | D12: Fixed Income | E12: 7.30% GOI 2053 | F12: IN002023Y456 | G12: INR | H12: 2000 | I12: 98.64 | J12: =H12*I12 -> 197280 | K12: Motilal Oswal | L12: IIFL Securities | M12: S7 Settlement | N12: Settled | P12: =Config!$B$1-B12 -> 460 | Q12: =IFERROR(INDEX('Failure Reference'!$C$4:$C$9,MATCH(O12,'Failure Reference'!$A$4:$A$9,0)),0) -> 0 | R12: =IF(N12="Settled",0,Q12+P12*0.5+IFERROR(INDEX(Config!$B$4:$B$7,MATCH(D12,Config!$A$4:$A$7,0)),1)+IF(C12-Config!$B$1<=1,5,0)) -> 0 | S12: =IF(R12=0,"Green",IF(R12<10,"Amber","Red")) -> Green | T12: =IF(N12="Settled","None",IF(C12-Config!$B$1<=0,"Overdue",IF(C12-Config!$B$1<=1,"Critical",IF(C12-Config!$B$1<=3,"High","Low")))) -> None | U12: =IF(R12=0,"",RANK(R12,$R$5:$R$104,0))
A13: TRD-009 | B13: 45704 | C13: 45705 | D13: Fixed Income | E13: 6.99% GOI 2026 | F13: IN002023Y789 | G13: INR | H13: 10000 | I13: 99.74 | J13: =H13*I13 -> 997400 | K13: ICICI Securities | L13: JM Financial | M13: S7 Settlement | N13: Settled | P13: =Config!$B$1-B13 -> 477 | Q13: =IFERROR(INDEX('Failure Reference'!$C$4:$C$9,MATCH(O13,'Failure Reference'!$A$4:$A$9,0)),0) -> 0 | R13: =IF(N13="Settled",0,Q13+P13*0.5+IFERROR(INDEX(Config!$B$4:$B$7,MATCH(D13,Config!$A$4:$A$7,0)),1)+IF(C13-Config!$B$1<=1,5,0)) -> 0 | S13: =IF(R13=0,"Green",IF(R13<10,"Amber","Red")) -> Green | T13: =IF(N13="Settled","None",IF(C13-Config!$B$1<=0,"Overdue",IF(C13-Config!$B$1<=1,"Critical",IF(C13-Config!$B$1<=3,"High","Low")))) -> None | U13: =IF(R13=0,"",RANK(R13,$R$5:$R$104,0))
A14: TRD-010 | B14: 45798 | C14: 45799 | D14: Commodities | E14: Gold Futures (MCX) | F14: N/A | G14: INR | H14: 10 | I14: 74044.27 | J14: =H14*I14 -> 740442.7 | K14: ICICI Securities | L14: Axis Securities | M14: S1 Validation | N14: In Progress | P14: =Config!$B$1-B14 -> 383 | Q14: =IFERROR(INDEX('Failure Reference'!$C$4:$C$9,MATCH(O14,'Failure Reference'!$A$4:$A$9,0)),0) -> 0 | R14: =IF(N14="Settled",0,Q14+P14*0.5+IFERROR(INDEX(Config!$B$4:$B$7,MATCH(D14,Config!$A$4:$A$7,0)),1)+IF(C14-Config!$B$1<=1,5,0)) -> 199 | S14: =IF(R14=0,"Green",IF(R14<10,"Amber","Red")) -> Red | T14: =IF(N14="Settled","None",IF(C14-Config!$B$1<=0,"Overdue",IF(C14-Config!$B$1<=1,"Critical",IF(C14-Config!$B$1<=3,"High","Low")))) -> Overdue | U14: =IF(R14=0,"",RANK(R14,$R$5:$R$104,0)) -> 22
A15: TRD-011 | B15: 45762 | C15: 45763 | D15: Equity | E15: ITC Ltd | F15: INE154A01025 | G15: INR | H15: 500 | I15: 417.69 | J15: =H15*I15 -> 208845 | K15: Angel One | L15: HDFC Securities | M15: S7 Settlement | N15: Settled | P15: =Config!$B$1-B15 -> 419 | Q15: =IFERROR(INDEX('Failure Reference'!$C$4:$C$9,MATCH(O15,'Failure Reference'!$A$4:$A$9,0)),0) -> 0 | R15: =IF(N15="Settled",0,Q15+P15*0.5+IFERROR(INDEX(Config!$B$4:$B$7,MATCH(D15,Config!$A$4:$A$7,0)),1)+IF(C15-Config!$B$1<=1,5,0)) -> 0 | S15: =IF(R15=0,"Green",IF(R15<10,"Amber","Red")) -> Green | T15: =IF(N15="Settled","None",IF(C15-Config!$B$1<=0,"Overdue",IF(C15-Config!$B$1<=1,"Critical",IF(C15-Config!$B$1<=3,"High","Low")))) -> None | U15: =IF(R15=0,"",RANK(R15,$R$5:$R$104,0))
A16: TRD-012 | B16: 45700 | C16: 45701 | D16: Commodities | E16: Natural Gas Futures (MCX) | F16: N/A | G16: USD | H16: 10 | I16: 3.04 | J16: =H16*I16 -> 30.4 | K16: IIFL Securities | L16: Axis Securities | M16: S7 Settlement | N16: Settled | P16: =Config!$B$1-B16 -> 481 | Q16: =IFERROR(INDEX('Failure Reference'!$C$4:$C$9,MATCH(O16,'Failure Reference'!$A$4:$A$9,0)),0) -> 0 | R16: =IF(N16="Settled",0,Q16+P16*0.5+IFERROR(INDEX(Config!$B$4:$B$7,MATCH(D16,Config!$A$4:$A$7,0)),1)+IF(C16-Config!$B$1<=1,5,0)) -> 0 | S16: =IF(R16=0,"Green",IF(R16<10,"Amber","Red")) -> Green | T16: =IF(N16="Settled","None",IF(C16-Config!$B$1<=0,"Overdue",IF(C16-Config!$B$1<=1,"Critical",IF(C16-Config!$B$1<=3,"High","Low")))) -> None | U16: =IF(R16=0,"",RANK(R16,$R$5:$R$104,0))
A17: TRD-013 | B17: 45766 | C17: 45767 | D17: Fixed Income | E17: Tata Steel Corp Bond | F17: INE081A08123 | G17: INR | H17: 25000 | I17: 102.96 | J17: =H17*I17 -> 2574000 | K17: IIFL Securities | L17: Motilal Oswal | M17: S7 Settlement | N17: Settled | P17: =Config!$B$1-B17 -> 415 | Q17: =IFERROR(INDEX('Failure Reference'!$C$4:$C$9,MATCH(O17,'Failure Reference'!$A$4:$A$9,0)),0) -> 0 | R17: =IF(N17="Settled",0,Q17+P17*0.5+IFERROR(INDEX(Config!$B$4:$B$7,MATCH(D17,Config!$A$4:$A$7,0)),1)+IF(C17-Config!$B$1<=1,5,0)) -> 0 | S17: =IF(R17=0,"Green",IF(R17<10,"Amber","Red")) -> Green | T17: =IF(N17="Settled","None",IF(C17-Config!$B$1<=0,"Overdue",IF(C17-Config!$B$1<=1,"Critical",IF(C17-Config!$B$1<=3,"High","Low")))) -> None | U17: =IF(R17=0,"",RANK(R17,$R$5:$R$104,0))
A18: TRD-014 | B18: 45706 | C18: 45707 | D18: Equity | E18: ICICI Bank Ltd | F18: INE090A01021 | G18: INR | H18: 200 | I18: 1172.5 | J18: =H18*I18 -> 234500 | K18: Nuvama Wealth | L18: JM Financial | M18: S7 Settlement | N18: Settled | P18: =Config!$B$1-B18 -> 475 | Q18: =IFERROR(INDEX('Failure Reference'!$C$4:$C$9,MATCH(O18,'Failure Reference'!$A$4:$A$9,0)),0) -> 0 | R18: =IF(N18="Settled",0,Q18+P18*0.5+IFERROR(INDEX(Config!$B$4:$B$7,MATCH(D18,Config!$A$4:$A$7,0)),1)+IF(C18-Config!$B$1<=1,5,0)) -> 0 | S18: =IF(R18=0,"Green",IF(R18<10,"Amber","Red")) -> Green | T18: =IF(N18="Settled","None",IF(C18-Config!$B$1<=0,"Overdue",IF(C18-Config!$B$1<=1,"Critical",IF(C18-Config!$B$1<=3,"High","Low")))) -> None | U18: =IF(R18=0,"",RANK(R18,$R$5:$R$104,0))
A19: TRD-015 | B19: 45673 | C19: 45674 | D19: Equity | E19: Maruti Suzuki | F19: INE585B01010 | G19: INR | H19: 300 | I19: 10751.81 | J19: =H19*I19 -> 3225543 | K19: Nuvama Wealth | L19: IIFL Securities | M19: S7 Settlement | N19: Settled | P19: =Config!$B$1-B19 -> 508 | Q19: =IFERROR(INDEX('Failure Reference'!$C$4:$C$9,MATCH(O19,'Failure Reference'!$A$4:$A$9,0)),0) -> 0 | R19: =IF(N19="Settled",0,Q19+P19*0.5+IFERROR(INDEX(Config!$B$4:$B$7,MATCH(D19,Config!$A$4:$A$7,0)),1)+IF(C19-Config!$B$1<=1,5,0)) -> 0 | S19: =IF(R19=0,"Green",IF(R19<10,"Amber","Red")) -> Green | T19: =IF(N19="Settled","None",IF(C19-Config!$B$1<=0,"Overdue",IF(C19-Config!$B$1<=1,"Critical",IF(C19-Config!$B$1<=3,"High","Low")))) -> None | U19: =IF(R19=0,"",RANK(R19,$R$5:$R$104,0))
... A21: TRD-017 | B21: 45705 | C21: 45706 | D21: Equity | E21: Infosys Ltd | F21: INE009A01021 | G21: INR | H21: 750 | I21: 1454.33 | J21: =H21*I21 -> 1090747.5 | K21: Kotak Securities | L21: IIFL Securities | M21: S7 Settlement | N21: Settled | P21: =Config!$B$1-B21 -> 476 | Q21: =IFERROR(INDEX('Failure Reference'!$C$4:$C$9,MATCH(O21,'Failure Reference'!$A$4:$A$9,0)),0) -> 0 | R21: =IF(N21="Settled",0,Q21+P21*0.5+IFERROR(INDEX(Config!$B$4:$B$7,MATCH(D21,Config!$A$4:$A$7,0)),1)+IF(C21-Config!$B$1<=1,5,0)) -> 0 | S21: =IF(R21=0,"Green",IF(R21<10,"Amber","Red")) -> Green | T21: =IF(N21="Settled","None",IF(C21-Config!$B$1<=0,"Overdue",IF(C21-Config!$B$1<=1,"Critical",IF(C21-Config!$B$1<=3,"High","Low")))) -> None | U21: =IF(R21=0,"",RANK(R21,$R$5:$R$104,0))
A22: TRD-018 | B22: 45688 | C22: 45689 | D22: Equity | E22: Sun Pharma | F22: INE044A01036 | G22: INR | H22: 750 | I22: 1344.98 | J22: =H22*I22 -> 1008735 | K22: Nuvama Wealth | L22: HDFC Securities | M22: S5 Matching | N22: Break | O22: Matching Break | P22: =Config!$B$1-B22 -> 493 | Q22: =IFERROR(INDEX('Failure Reference'!$C$4:$C$9,MATCH(O22,'Failure Reference'!$A$4:$A$9,0)),0) -> 8 | R22: =IF(N22="Settled",0,Q22+P22*0.5+IFERROR(INDEX(Config!$B$4:$B$7,MATCH(D22,Config!$A$4:$A$7,0)),1)+IF(C22-Config!$B$1<=1,5,0)) -> 260.5 | S22: =IF(R22=0,"Green",IF(R22<10,"Amber","Red")) -> Red | T22: =IF(N22="Settled","None",IF(C22-Config!$B$1<=0,"Overdue",IF(C22-Config!$B$1<=1,"Critical",IF(C22-Config!$B$1<=3,"High","Low")))) -> Overdue | U22: =IF(R22=0,"",RANK(R22,$R$5:$R$104,0)) -> 4
A23: TRD-019 | B23: 45816 | C23: 45817 | D23: Equity | E23: Infosys Ltd | F23: INE009A01021 | G23: INR | H23: 500 | I23: 1543.92 | J23: =H23*I23 -> 771960 | K23: Nuvama Wealth | L23: JM Financial | M23: S2 Enrichment | N23: In Progress | P23: =Config!$B$1-B23 -> 365 | Q23: =IFERROR(INDEX('Failure Reference'!$C$4:$C$9,MATCH(O23,'Failure Reference'!$A$4:$A$9,0)),0) -> 0 | R23: =IF(N23="Settled",0,Q23+P23*0.5+IFERROR(INDEX(Config!$B$4:$B$7,MATCH(D23,Config!$A$4:$A$7,0)),1)+IF(C23-Config!$B$1<=1,5,0)) -> 188.5 | S23: =IF(R23=0,"Green",IF(R23<10,"Amber","Red")) -> Red | T23: =IF(N23="Settled","None",IF(C23-Config!$B$1<=0,"Overdue",IF(C23-Config!$B$1<=1,"Critical",IF(C23-Config!$B$1<=3,"High","Low")))) -> Overdue | U23: =IF(R23=0,"",RANK(R23,$R$5:$R$104,0)) -> 25
A24: TRD-020 | B24: 45724 | C24: 45725 | D24: Fixed Income | E24: 7.30% GOI 2053 | F24: IN002023Y456 | G24: INR | H24: 5000 | I24: 97.47 | J24: =H24*I24 -> 487350 | K24: Angel One | L24: Motilal Oswal | M24: S7 Settlement | N24: Settled | P24: =Config!$B$1-B24 -> 457 | Q24: =IFERROR(INDEX('Failure Reference'!$C$4:$C$9,MATCH(O24,'Failure Reference'!$A$4:$A$9,0)),0) -> 0 | R24: =IF(N24="Settled",0,Q24+P24*0.5+IFERROR(INDEX(Config!$B$4:$B$7,MATCH(D24,Config!$A$4:$A$7,0)),1)+IF(C24-Config!$B$1<=1,5,0)) -> 0 | S24: =IF(R24=0,"Green",IF(R24<10,"Amber","Red")) -> Green | T24: =IF(N24="Settled","None",IF(C24-Config!$B$1<=0,"Overdue",IF(C24-Config!$B$1<=1,"Critical",IF(C24-Config!$B$1<=3,"High","Low")))) -> None | U24: =IF(R24=0,"",RANK(R24,$R$5:$R$104,0))
A25: TRD-021 | B25: 45829 | C25: 45830 | D25: Equity | E25: Bajaj Finance Ltd | F25: INE296A01024 | G25: INR | H25: 300 | I25: 7094.52 | J25: =H25*I25 -> 2128356 | K25: ICICI Securities | L25: HDFC Securities | M25: S7 Settlement | N25: Settled | P25: =Config!$B$1-B25 -> 352 | Q25: =IFERROR(INDEX('Failure Reference'!$C$4:$C$9,MATCH(O25,'Failure Reference'!$A$4:$A$9,0)),0) -> 0 | R25: =IF(N25="Settled",0,Q25+P25*0.5+IFERROR(INDEX(Config!$B$4:$B$7,MATCH(D25,Config!$A$4:$A$7,0)),1)+IF(C25-Config!$B$1<=1,5,0)) -> 0 | S25: =IF(R25=0,"Green",IF(R25<10,"Amber","Red")) -> Green | T25: =IF(N25="Settled","None",IF(C25-Config!$B$1<=0,"Overdue",IF(C25-Config!$B$1<=1,"Critical",IF(C25-Config!$B$1<=3,"High","Low")))) -> None | U25: =IF(R25=0,"",RANK(R25,$R$5:$R$104,0))
A26: TRD-022 | B26: 45775 | C26: 45776 | D26: Commodities | E26: Copper Futures (MCX) | F26: N/A | G26: INR | H26: 200 | I26: 4.55 | J26: =H26*I26 -> 910 | K26: JM Financial | L26: Kotak Securities | M26: S7 Settlement | N26: Settled | P26: =Config!$B$1-B26 -> 406 | Q26: =IFERROR(INDEX('Failure Reference'!$C$4:$C$9,MATCH(O26,'Failure Reference'!$A$4:$A$9,0)),0) -> 0 | R26: =IF(N26="Settled",0,Q26+P26*0.5+IFERROR(INDEX(Config!$B$4:$B$7,MATCH(D26,Config!$A$4:$A$7,0)),1)+IF(C26-Config!$B$1<=1,5,0)) -> 0 | S26: =IF(R26=0,"Green",IF(R26<10,"Amber","Red")) -> Green | T26: =IF(N26="Settled","None",IF(C26-Config!$B$1<=0,"Overdue",IF(C26-Config!$B$1<=1,"Critical",IF(C26-Config!$B$1<=3,"High","Low")))) -> None | U26: =IF(R26=0,"",RANK(R26,$R$5:$R$104,0))
A27: TRD-023 | B27: 45787 | C27: 45788 | D27: Equity | E27: ICICI Bank Ltd | F27: INE090A01021 | G27: INR | H27: 200 | I27: 1168.53 | J27: =H27*I27 -> 233706 | K27: ICICI Securities | L27: Axis Securities | M27: S7 Settlement | N27: Settled | P27: =Config!$B$1-B27 -> 394 | Q27: =IFERROR(INDEX('Failure Reference'!$C$4:$C$9,MATCH(O27,'Failure Reference'!$A$4:$A$9,0)),0) -> 0 | R27: =IF(N27="Settled",0,Q27+P27*0.5+IFERROR(INDEX(Config!$B$4:$B$7,MATCH(D27,Config!$A$4:$A$7,0)),1)+IF(C27-Config!$B$1<=1,5,0)) -> 0 | S27: =IF(R27=0,"Green",IF(R27<10,"Amber","Red")) -> Green | T27: =IF(N27="Settled","None",IF(C27-Config!$B$1<=0,"Overdue",IF(C27-Config!$B$1<=1,"Critical",IF(C27-Config!$B$1<=3,"High","Low")))) -> None | U27: =IF(R27=0,"",RANK(R27,$R$5:$R$104,0))
A28: TRD-024 | B28: 45752 | C28: 45753 | D28: Equity | E28: ICICI Bank Ltd | F28: INE090A01021 | G28: INR | H28: 200 | I28: 1113.08 | J28: =H28*I28 -> 222616 | K28: JM Financial | L28: Axis Securities | M28: S5 Matching | N28: Break | O28: Matching Break | P28: =Config!$B$1-B28 -> 429 | Q28: =IFERROR(INDEX('Failure Reference'!$C$4:$C$9,MATCH(O28,'Failure Reference'!$A$4:$A$9,0)),0) -> 8 | R28: =IF(N28="Settled",0,Q28+P28*0.5+IFERROR(INDEX(Config!$B$4:$B$7,MATCH(D28,Config!$A$4:$A$7,0)),1)+IF(C28-Config!$B$1<=1,5,0)) -> 228.5 | S28: =IF(R28=0,"Green",IF(R28<10,"Amber","Red")) -> Red | T28: =IF(N28="Settled","None",IF(C28-Config!$B$1<=0,"Overdue",IF(C28-Config!$B$1<=1,"Critical",IF(C28-Config!$B$1<=3,"High","Low")))) -> Overdue | U28: =IF(R28=0,"",RANK(R28,$R$5:$R$104,0)) -> 16
A29: TRD-025 | B29: 45814 | C29: 45815 | D29: Derivatives | E29: EURINR Futures | F29: N/A | G29: INR | H29: 1 | I29: 91.16 | J29: =H29*I29 -> 91.16 | K29: JM Financial | L29: Axis Securities | M29: S5 Matching | N29: In Progress | P29: =Config!$B$1-B29 -> 367 | Q29: =IFERROR(INDEX('Failure Reference'!$C$4:$C$9,MATCH(O29,'Failure Reference'!$A$4:$A$9,0)),0) -> 0 | R29: =IF(N29="Settled",0,Q29+P29*0.5+IFERROR(INDEX(Config!$B$4:$B$7,MATCH(D29,Config!$A$4:$A$7,0)),1)+IF(C29-Config!$B$1<=1,5,0)) -> 190.5 | S29: =IF(R29=0,"Green",IF(R29<10,"Amber","Red")) -> Red | T29: =IF(N29="Settled","None",IF(C29-Config!$B$1<=0,"Overdue",IF(C29-Config!$B$1<=1,"Critical",IF(C29-Config!$B$1<=3,"High","Low")))) -> Overdue | U29: =IF(R29=0,"",RANK(R29,$R$5:$R$104,0)) -> 24
A30: TRD-026 | B30: 45684 | C30: 45685 | D30: Equity | E30: Sun Pharma | F30: INE044A01036 | G30: INR | H30: 200 | I30: 1347.5 | J30: =H30*I30 -> 269500 | K30: ICICI Securities | L30: Nuvama Wealth | M30: S7 Settlement | N30: Settled | P30: =Config!$B$1-B30 -> 497 | Q30: =IFERROR(INDEX('Failure Reference'!$C$4:$C$9,MATCH(O30,'Failure Reference'!$A$4:$A$9,0)),0) -> 0 | R30: =IF(N30="Settled",0,Q30+P30*0.5+IFERROR(INDEX(Config!$B$4:$B$7,MATCH(D30,Config!$A$4:$A$7,0)),1)+IF(C30-Config!$B$1<=1,5,0)) -> 0 | S30: =IF(R30=0,"Green",IF(R30<10,"Amber","Red")) -> Green | T30: =IF(N30="Settled","None",IF(C30-Config!$B$1<=0,"Overdue",IF(C30-Config!$B$1<=1,"Critical",IF(C30-Config!$B$1<=3,"High","Low")))) -> None | U30: =IF(R30=0,"",RANK(R30,$R$5:$R$104,0))
A31: TRD-027 | B31: 45697 | C31: 45698 | D31: Equity | E31: ICICI Bank Ltd | F31: INE090A01021 | G31: INR | H31: 300 | I31: 1131.74 | J31: =H31*I31 -> 339522 | K31: Sharekhan | L31: Kotak Securities | M31: S5 Matching | N31: In Progress | P31: =Config!$B$1-B31 -> 484 | Q31: =IFERROR(INDEX('Failure Reference'!$C$4:$C$9,MATCH(O31,'Failure Reference'!$A$4:$A$9,0)),0) -> 0 | R31: =IF(N31="Settled",0,Q31+P31*0.5+IFERROR(INDEX(Config!$B$4:$B$7,MATCH(D31,Config!$A$4:$A$7,0)),1)+IF(C31-Config!$B$1<=1,5,0)) -> 248 | S31: =IF(R31=0,"Green",IF(R31<10,"Amber","Red")) -> Red | T31: =IF(N31="Settled","None",IF(C31-Config!$B$1<=0,"Overdue",IF(C31-Config!$B$1<=1,"Critical",IF(C31-Config!$B$1<=3,"High","Low")))) -> Overdue | U31: =IF(R31=0,"",RANK(R31,$R$5:$R$104,0)) -> 10
A32: TRD-028 | B32: 45820 | C32: 45821 | D32: Equity | E32: Wipro Ltd | F32: INE075A01022 | G32: INR | H32: 300 | I32: 475.26 | J32: =H32*I32 -> 142578 | K32: Axis Securities | L32: HDFC Securities | M32: S7 Settlement | N32: Settled | P32: =Config!$B$1-B32 -> 361 | Q32: =IFERROR(INDEX('Failure Reference'!$C$4:$C$9,MATCH(O32,'Failure Reference'!$A$4:$A$9,0)),0) -> 0 | R32: =IF(N32="Settled",0,Q32+P32*0.5+IFERROR(INDEX(Config!$B$4:$B$7,MATCH(D32,Config!$A$4:$A$7,0)),1)+IF(C32-Config!$B$1<=1,5,0)) -> 0 | S32: =IF(R32=0,"Green",IF(R32<10,"Amber","Red")) -> Green | T32: =IF(N32="Settled","None",IF(C32-Config!$B$1<=0,"Overdue",IF(C32-Config!$B$1<=1,"Critical",IF(C32-Config!$B$1<=3,"High","Low")))) -> None | U32: =IF(R32=0,"",RANK(R32,$R$5:$R$104,0))
A33: TRD-029 | B33: 45681 | C33: 45682 | D33: Commodities | E33: Natural Gas Futures (MCX) | F33: N/A | G33: USD | H33: 50 | I33: 2.67 | J33: =H33*I33 -> 133.5 | K33: Motilal Oswal | L33: Sharekhan | M33: S1 Validation | N33: In Progress | P33: =Config!$B$1-B33 -> 500 | Q33: =IFERROR(INDEX('Failure Reference'!$C$4:$C$9,MATCH(O33,'Failure Reference'!$A$4:$A$9,0)),0) -> 0 | R33: =IF(N33="Settled",0,Q33+P33*0.5+IFERROR(INDEX(Config!$B$4:$B$7,MATCH(D33,Config!$A$4:$A$7,0)),1)+IF(C33-Config!$B$1<=1,5,0)) -> 257.5 | S33: =IF(R33=0,"Green",IF(R33<10,"Amber","Red")) -> Red | T33: =IF(N33="Settled","None",IF(C33-Config!$B$1<=0,"Overdue",IF(C33-Config!$B$1<=1,"Critical",IF(C33-Config!$B$1<=3,"High","Low")))) -> Overdue | U33: =IF(R33=0,"",RANK(R33,$R$5:$R$104,0)) -> 6
A34: TRD-030 | B34: 45771 | C34: 45772 | D34: Fixed Income | E34: T-Bill 182D | F34: IN002024T002 | G34: INR | H34: 10000 | I34: 99.04 | J34: =H34*I34 -> 990400 | K34: ICICI Securities | L34: Motilal Oswal | M34: S7 Settlement | N34: Settled | P34: =Config!$B$1-B34 -> 410 | Q34: =IFERROR(INDEX('Failure Reference'!$C$4:$C$9,MATCH(O34,'Failure Reference'!$A$4:$A$9,0)),0) -> 0 | R34: =IF(N34="Settled",0,Q34+P34*0.5+IFERROR(INDEX(Config!$B$4:$B$7,MATCH(D34,Config!$A$4:$A$7,0)),1)+IF(C34-Config!$B$1<=1,5,0)) -> 0 | S34: =IF(R34=0,"Green",IF(R34<10,"Amber","Red")) -> Green | T34: =IF(N34="Settled","None",IF(C34-Config!$B$1<=0,"Overdue",IF(C34-Config!$B$1<=1,"Critical",IF(C34-Config!$B$1<=3,"High","Low")))) -> None | U34: =IF(R34=0,"",RANK(R34,$R$5:$R$104,0))
A35: TRD-031 | B35: 45834 | C35: 45835 | D35: Equity | E35: Sun Pharma | F35: INE044A01036 | G35: INR | H35: 200 | I35: 1386.29 | J35: =H35*I35 -> 277258 | K35: Sharekhan | L35: Nuvama Wealth | M35: S7 Settlement | N35: Settled | P35: =Config!$B$1-B35 -> 347 | Q35: =IFERROR(INDEX('Failure Reference'!$C$4:$C$9,MATCH(O35,'Failure Reference'!$A$4:$A$9,0)),0) -> 0 | R35: =IF(N35="Settled",0,Q35+P35*0.5+IFERROR(INDEX(Config!$B$4:$B$7,MATCH(D35,Config!$A$4:$A$7,0)),1)+IF(C35-Config!$B$1<=1,5,0)) -> 0 | S35: =IF(R35=0,"Green",IF(R35<10,"Amber","Red")) -> Green | T35: =IF(N35="Settled","None",IF(C35-Config!$B$1<=0,"Overdue",IF(C35-Config!$B$1<=1,"Critical",IF(C35-Config!$B$1<=3,"High","Low")))) -> None | U35: =IF(R35=0,"",RANK(R35,$R$5:$R$104,0))
A36: TRD-032 | B36: 45695 | C36: 45696 | D36: Equity | E36: Larsen & Toubro | F36: INE018A01030 | G36: INR | H36: 200 | I36: 3101.09 | J36: =H36*I36 -> 620218 | K36: Sharekhan | L36: HDFC Securities | M36: S7 Settlement | N36: Settled | P36: =Config!$B$1-B36 -> 486 | Q36: =IFERROR(INDEX('Failure Reference'!$C$4:$C$9,MATCH(O36,'Failure Reference'!$A$4:$A$9,0)),0) -> 0 | R36: =IF(N36="Settled",0,Q36+P36*0.5+IFERROR(INDEX(Config!$B$4:$B$7,MATCH(D36,Config!$A$4:$A$7,0)),1)+IF(C36-Config!$B$1<=1,5,0)) -> 0 | S36: =IF(R36=0,"Green",IF(R36<10,"Amber","Red")) -> Green | T36: =IF(N36="Settled","None",IF(C36-Config!$B$1<=0,"Overdue",IF(C36-Config!$B$1<=1,"Critical",IF(C36-Config!$B$1<=3,"High","Low")))) -> None | U36: =IF(R36=0,"",RANK(R36,$R$5:$R$104,0))
A37: TRD-033 | B37: 45749 | C37: 45750 | D37: Derivatives | E37: Bank Nifty Futures | F37: N/A | G37: INR | H37: 50 | I37: 47475.64 | J37: =H37*I37 -> 2373782 | K37: ICICI Securities | L37: Angel One | M37: S7 Settlement | N37: Settled | P37: =Config!$B$1-B37 -> 432 | Q37: =IFERROR(INDEX('Failure Reference'!$C$4:$C$9,MATCH(O37,'Failure Reference'!$A$4:$A$9,0)),0) -> 0 | R37: =IF(N37="Settled",0,Q37+P37*0.5+IFERROR(INDEX(Config!$B$4:$B$7,MATCH(D37,Config!$A$4:$A$7,0)),1)+IF(C37-Config!$B$1<=1,5,0)) -> 0 | S37: =IF(R37=0,"Green",IF(R37<10,"Amber","Red")) -> Green | T37: =IF(N37="Settled","None",IF(C37-Config!$B$1<=0,"Overdue",IF(C37-Config!$B$1<=1,"Critical",IF(C37-Config!$B$1<=3,"High","Low")))) -> None | U37: =IF(R37=0,"",RANK(R37,$R$5:$R$104,0))
A38: TRD-034 | B38: 45801 | C38: 45802 | D38: Derivatives | E38: USDINR Futures | F38: N/A | G38: INR | H38: 20 | I38: 84.75 | J38: =H38*I38 -> 1695 | K38: Kotak Securities | L38: Motilal Oswal | M38: S7 Settlement | N38: Settled | P38: =Config!$B$1-B38 -> 380 | Q38: =IFERROR(INDEX('Failure Reference'!$C$4:$C$9,MATCH(O38,'Failure Reference'!$A$4:$A$9,0)),0) -> 0 | R38: =IF(N38="Settled",0,Q38+P38*0.5+IFERROR(INDEX(Config!$B$4:$B$7,MATCH(D38,Config!$A$4:$A$7,0)),1)+IF(C38-Config!$B$1<=1,5,0)) -> 0 | S38: =IF(R38=0,"Green",IF(R38<10,"Amber","Red")) -> Green | T38: =IF(N38="Settled","None",IF(C38-Config!$B$1<=0,"Overdue",IF(C38-Config!$B$1<=1,"Critical",IF(C38-Config!$B$1<=3,"High","Low")))) -> None | U38: =IF(R38=0,"",RANK(R38,$R$5:$R$104,0))
A39: TRD-035 | B39: 45703 | C39: 45704 | D39: Equity | E39: Sun Pharma | F39: INE044A01036 | G39: INR | H39: 500 | I39: 1314.42 | J39: =H39*I39 -> 657210 | K39: Sharekhan | L39: IIFL Securities | M39: S7 Settlement | N39: Settled | P39: =Config!$B$1-B39 -> 478 | Q39: =IFERROR(INDEX('Failure Reference'!$C$4:$C$9,MATCH(O39,'Failure Reference'!$A$4:$A$9,0)),0) -> 0 | R39: =IF(N39="Settled",0,Q39+P39*0.5+IFERROR(INDEX(Config!$B$4:$B$7,MATCH(D39,Config!$A$4:$A$7,0)),1)+IF(C39-Config!$B$1<=1,5,0)) -> 0 | S39: =IF(R39=0,"Green",IF(R39<10,"Amber","Red")) -> Green | T39: =IF(N39="Settled","None",IF(C39-Config!$B$1<=0,"Overdue",IF(C39-Config!$B$1<=1,"Critical",IF(C39-Config!$B$1<=3,"High","Low")))) -> None | U39: =IF(R39=0,"",RANK(R39,$R$5:$R$104,0))
A40: TRD-036 | B40: 45829 | C40: 45830 | D40: Derivatives | E40: Bank Nifty Futures | F40: N/A | G40: INR | H40: 5 | I40: 47214.4 | J40: =H40*I40 -> 236072 | K40: ICICI Securities | L40: IIFL Securities | M40: S7 Settlement | N40: Settled | P40: =Config!$B$1-B40 -> 352 | Q40: =IFERROR(INDEX('Failure Reference'!$C$4:$C$9,MATCH(O40,'Failure Reference'!$A$4:$A$9,0)),0) -> 0 | R40: =IF(N40="Settled",0,Q40+P40*0.5+IFERROR(INDEX(Config!$B$4:$B$7,MATCH(D40,Config!$A$4:$A$7,0)),1)+IF(C40-Config!$B$1<=1,5,0)) -> 0 | S40: =IF(R40=0,"Green",IF(R40<10,"Amber","Red")) -> Green | T40: =IF(N40="Settled","None",IF(C40-Config!$B$1<=0,"Overdue",IF(C40-Config!$B$1<=1,"Critical",IF(C40-Config!$B$1<=3,"High","Low")))) -> None | U40: =IF(R40=0,"",RANK(R40,$R$5:$R$104,0))
A41: TRD-037 | B41: 45667 | C41: 45668 | D41: Commodities | E41: Natural Gas Futures (MCX) | F41: N/A | G41: USD | H41: 25 | I41: 2.73 | J41: =H41*I41 -> 68.25 | K41: Sharekhan | L41: Axis Securities | M41: S7 Settlement | N41: Break | O41: Settlement Fail | P41: =Config!$B$1-B41 -> 514 | Q41: =IFERROR(INDEX('Failure Reference'!$C$4:$C$9,MATCH(O41,'Failure Reference'!$A$4:$A$9,0)),0) -> 10 | R41: =IF(N41="Settled",0,Q41+P41*0.5+IFERROR(INDEX(Config!$B$4:$B$7,MATCH(D41,Config!$A$4:$A$7,0)),1)+IF(C41-Config!$B$1<=1,5,0)) -> 274.5 | S41: =IF(R41=0,"Green",IF(R41<10,"Amber","Red")) -> Red | T41: =IF(N41="Settled","None",IF(C41-Config!$B$1<=0,"Overdue",IF(C41-Config!$B$1<=1,"Critical",IF(C41-Config!$B$1<=3,"High","Low")))) -> Overdue | U41: =IF(R41=0,"",RANK(R41,$R$5:$R$104,0)) -> 1
A42: TRD-038 | B42: 45716 | C42: 45717 | D42: Derivatives | E42: Bank Nifty Futures | F42: N/A | G42: INR | H42: 1 | I42: 48662.82 | J42: =H42*I42 -> 48662.82 | K42: Angel One | L42: Sharekhan | M42: S7 Settlement | N42: Settled | P42: =Config!$B$1-B42 -> 465 | Q42: =IFERROR(INDEX('Failure Reference'!$C$4:$C$9,MATCH(O42,'Failure Reference'!$A$4:$A$9,0)),0) -> 0 | R42: =IF(N42="Settled",0,Q42+P42*0.5+IFERROR(INDEX(Config!$B$4:$B$7,MATCH(D42,Config!$A$4:$A$7,0)),1)+IF(C42-Config!$B$1<=1,5,0)) -> 0 | S42: =IF(R42=0,"Green",IF(R42<10,"Amber","Red")) -> Green | T42: =IF(N42="Settled","None",IF(C42-Config!$B$1<=0,"Overdue",IF(C42-Config!$B$1<=1,"Critical",IF(C42-Config!$B$1<=3,"High","Low")))) -> None | U42: =IF(R42=0,"",RANK(R42,$R$5:$R$104,0))
A43: TRD-039 | B43: 45729 | C43: 45730 | D43: Fixed Income | E43: HDFC Ltd Corp Bond | F43: INE001A08145 | G43: INR | H43: 1000 | I43: 103.7 | J43: =H43*I43 -> 103700 | K43: Axis Securities | L43: Angel One | M43: S5 Matching | N43: In Progress | P43: =Config!$B$1-B43 -> 452 | Q43: =IFERROR(INDEX('Failure Reference'!$C$4:$C$9,MATCH(O43,'Failure Reference'!$A$4:$A$9,0)),0) -> 0 | R43: =IF(N43="Settled",0,Q43+P43*0.5+IFERROR(INDEX(Config!$B$4:$B$7,MATCH(D43,Config!$A$4:$A$7,0)),1)+IF(C43-Config!$B$1<=1,5,0)) -> 232.5 | S43: =IF(R43=0,"Green",IF(R43<10,"Amber","Red")) -> Red | T43: =IF(N43="Settled","None",IF(C43-Config!$B$1<=0,"Overdue",IF(C43-Config!$B$1<=1,"Critical",IF(C43-Config!$B$1<=3,"High","Low")))) -> Overdue | U43: =IF(R43=0,"",RANK(R43,$R$5:$R$104,0)) -> 13
A44: TRD-040 | B44: 45788 | C44: 45789 | D44: Fixed Income | E44: T-Bill 91D | F44: IN002024T001 | G44: INR | H44: 25000 | I44: 98.83 | J44: =H44*I44 -> 2470750 | K44: HDFC Securities | L44: Motilal Oswal | M44: S7 Settlement | N44: Settled | P44: =Config!$B$1-B44 -> 393 | Q44: =IFERROR(INDEX('Failure Reference'!$C$4:$C$9,MATCH(O44,'Failure Reference'!$A$4:$A$9,0)),0) -> 0 | R44: =IF(N44="Settled",0,Q44+P44*0.5+IFERROR(INDEX(Config!$B$4:$B$7,MATCH(D44,Config!$A$4:$A$7,0)),1)+IF(C44-Config!$B$1<=1,5,0)) -> 0 | S44: =IF(R44=0,"Green",IF(R44<10,"Amber","Red")) -> Green | T44: =IF(N44="Settled","None",IF(C44-Config!$B$1<=0,"Overdue",IF(C44-Config!$B$1<=1,"Critical",IF(C44-Config!$B$1<=3,"High","Low")))) -> None | U44: =IF(R44=0,"",RANK(R44,$R$5:$R$104,0))
A45: TRD-041 | B45: 45724 | C45: 45725 | D45: Commodities | E45: Silver Futures (MCX) | F45: N/A | G45: USD | H45: 200 | I45: 93166.05 | J45: =H45*I45 -> 18633210 | K45: HDFC Securities | L45: Motilal Oswal | M45: S7 Settlement | N45: Settled | P45: =Config!$B$1-B45 -> 457 | Q45: =IFERROR(INDEX('Failure Reference'!$C$4:$C$9,MATCH(O45,'Failure Reference'!$A$4:$A$9,0)),0) -> 0 | R45: =IF(N45="Settled",0,Q45+P45*0.5+IFERROR(INDEX(Config!$B$4:$B$7,MATCH(D45,Config!$A$4:$A$7,0)),1)+IF(C45-Config!$B$1<=1,5,0)) -> 0 | S45: =IF(R45=0,"Green",IF(R45<10,"Amber","Red")) -> Green | T45: =IF(N45="Settled","None",IF(C45-Config!$B$1<=0,"Overdue",IF(C45-Config!$B$1<=1,"Critical",IF(C45-Config!$B$1<=3,"High","Low")))) -> None | U45: =IF(R45=0,"",RANK(R45,$R$5:$R$104,0))
A46: TRD-042 | B46: 45810 | C46: 45811 | D46: Derivatives | E46: USDINR Futures | F46: N/A | G46: INR | H46: 5 | I46: 84.65 | J46: =H46*I46 -> 423.25 | K46: Sharekhan | L46: IIFL Securities | M46: S7 Settlement | N46: Settled | P46: =Config!$B$1-B46 -> 371 | Q46: =IFERROR(INDEX('Failure Reference'!$C$4:$C$9,MATCH(O46,'Failure Reference'!$A$4:$A$9,0)),0) -> 0 | R46: =IF(N46="Settled",0,Q46+P46*0.5+IFERROR(INDEX(Config!$B$4:$B$7,MATCH(D46,Config!$A$4:$A$7,0)),1)+IF(C46-Config!$B$1<=1,5,0)) -> 0 | S46: =IF(R46=0,"Green",IF(R46<10,"Amber","Red")) -> Green | T46: =IF(N46="Settled","None",IF(C46-Config!$B$1<=0,"Overdue",IF(C46-Config!$B$1<=1,"Critical",IF(C46-Config!$B$1<=3,"High","Low")))) -> None | U46: =IF(R46=0,"",RANK(R46,$R$5:$R$104,0))
A47: TRD-043 | B47: 45813 | C47: 45814 | D47: Fixed Income | E47: T-Bill 182D | F47: IN002024T002 | G47: INR | H47: 1000 | I47: 98.35 | J47: =H47*I47 -> 98350 | K47: Nuvama Wealth | L47: Kotak Securities | M47: S7 Settlement | N47: Settled | P47: =Config!$B$1-B47 -> 368 | Q47: =IFERROR(INDEX('Failure Reference'!$C$4:$C$9,MATCH(O47,'Failure Reference'!$A$4:$A$9,0)),0) -> 0 | R47: =IF(N47="Settled",0,Q47+P47*0.5+IFERROR(INDEX(Config!$B$4:$B$7,MATCH(D47,Config!$A$4:$A$7,0)),1)+IF(C47-Config!$B$1<=1,5,0)) -> 0 | S47: =IF(R47=0,"Green",IF(R47<10,"Amber","Red")) -> Green | T47: =IF(N47="Settled","None",IF(C47-Config!$B$1<=0,"Overdue",IF(C47-Config!$B$1<=1,"Critical",IF(C47-Config!$B$1<=3,"High","Low")))) -> None | U47: =IF(R47=0,"",RANK(R47,$R$5:$R$104,0))
A48: TRD-044 | B48: 45723 | C48: 45724 | D48: Equity | E48: Reliance Industries Ltd | F48: INE002A01018 | G48: INR | H48: 1000 | I48: 2831.78 | J48: =H48*I48 -> 2831780 | K48: JM Financial | L48: Nuvama Wealth | M48: S7 Settlement | N48: Settled | P48: =Config!$B$1-B48 -> 458 | Q48: =IFERROR(INDEX('Failure Reference'!$C$4:$C$9,MATCH(O48,'Failure Reference'!$A$4:$A$9,0)),0) -> 0 | R48: =IF(N48="Settled",0,Q48+P48*0.5+IFERROR(INDEX(Config!$B$4:$B$7,MATCH(D48,Config!$A$4:$A$7,0)),1)+IF(C48-Config!$B$1<=1,5,0)) -> 0 | S48: =IF(R48=0,"Green",IF(R48<10,"Amber","Red")) -> Green | T48: =IF(N48="Settled","None",IF(C48-Config!$B$1<=0,"Overdue",IF(C48-Config!$B$1<=1,"Critical",IF(C48-Config!$B$1<=3,"High","Low")))) -> None | U48: =IF(R48=0,"",RANK(R48,$R$5:$R$104,0))
A49: TRD-045 | B49: 45833 | C49: 45834 | D49: Equity | E49: Maruti Suzuki | F49: INE585B01010 | G49: INR | H49: 1000 | I49: 11516.67 | J49: =H49*I49 -> 11516670 | K49: Kotak Securities | L49: Angel One | M49: S7 Settlement | N49: Settled | P49: =Config!$B$1-B49 -> 348 | Q49: =IFERROR(INDEX('Failure Reference'!$C$4:$C$9,MATCH(O49,'Failure Reference'!$A$4:$A$9,0)),0) -> 0 | R49: =IF(N49="Settled",0,Q49+P49*0.5+IFERROR(INDEX(Config!$B$4:$B$7,MATCH(D49,Config!$A$4:$A$7,0)),1)+IF(C49-Config!$B$1<=1,5,0)) -> 0 | S49: =IF(R49=0,"Green",IF(R49<10,"Amber","Red")) -> Green | T49: =IF(N49="Settled","None",IF(C49-Config!$B$1<=0,"Overdue",IF(C49-Config!$B$1<=1,"Critical",IF(C49-Config!$B$1<=3,"High","Low")))) -> None | U49: =IF(R49=0,"",RANK(R49,$R$5:$R$104,0))
A50: TRD-046 | B50: 45768 | C50: 45769 | D50: Equity | E50: Infosys Ltd | F50: INE009A01021 | G50: INR | H50: 1000 | I50: 1583.96 | J50: =H50*I50 -> 1583960 | K50: Nuvama Wealth | L50: Sharekhan | M50: S7 Settlement | N50: Settled | P50: =Config!$B$1-B50 -> 413 | Q50: =IFERROR(INDEX('Failure Reference'!$C$4:$C$9,MATCH(O50,'Failure Reference'!$A$4:$A$9,0)),0) -> 0 | R50: =IF(N50="Settled",0,Q50+P50*0.5+IFERROR(INDEX(Config!$B$4:$B$7,MATCH(D50,Config!$A$4:$A$7,0)),1)+IF(C50-Config!$B$1<=1,5,0)) -> 0 | S50: =IF(R50=0,"Green",IF(R50<10,"Amber","Red")) -> Green | T50: =IF(N50="Settled","None",IF(C50-Config!$B$1<=0,"Overdue",IF(C50-Config!$B$1<=1,"Critical",IF(C50-Config!$B$1<=3,"High","Low")))) -> None | U50: =IF(R50=0,"",RANK(R50,$R$5:$R$104,0))
A51: TRD-047 | B51: 45827 | C51: 45828 | D51: Equity | E51: Wipro Ltd | F51: INE075A01022 | G51: INR | H51: 100 | I51: 485.44 | J51: =H51*I51 -> 48544 | K51: Axis Securities | L51: Nuvama Wealth | M51: S7 Settlement | N51: Settled | P51: =Config!$B$1-B51 -> 354 | Q51: =IFERROR(INDEX('Failure Reference'!$C$4:$C$9,MATCH(O51,'Failure Reference'!$A$4:$A$9,0)),0) -> 0 | R51: =IF(N51="Settled",0,Q51+P51*0.5+IFERROR(INDEX(Config!$B$4:$B$7,MATCH(D51,Config!$A$4:$A$7,0)),1)+IF(C51-Config!$B$1<=1,5,0)) -> 0 | S51: =IF(R51=0,"Green",IF(R51<10,"Amber","Red")) -> Green | T51: =IF(N51="Settled","None",IF(C51-Config!$B$1<=0,"Overdue",IF(C51-Config!$B$1<=1,"Critical",IF(C51-Config!$B$1<=3,"High","Low")))) -> None | U51: =IF(R51=0,"",RANK(R51,$R$5:$R$104,0))
A52: TRD-048 | B52: 45737 | C52: 45738 | D52: Fixed Income | E52: Tata Steel Corp Bond | F52: INE081A08123 | G52: INR | H52: 10000 | I52: 101.59 | J52: =H52*I52 -> 1015900 | K52: Axis Securities | L52: Nuvama Wealth | M52: S7 Settlement | N52: Settled | P52: =Config!$B$1-B52 -> 444 | Q52: =IFERROR(INDEX('Failure Reference'!$C$4:$C$9,MATCH(O52,'Failure Reference'!$A$4:$A$9,0)),0) -> 0 | R52: =IF(N52="Settled",0,Q52+P52*0.5+IFERROR(INDEX(Config!$B$4:$B$7,MATCH(D52,Config!$A$4:$A$7,0)),1)+IF(C52-Config!$B$1<=1,5,0)) -> 0 | S52: =IF(R52=0,"Green",IF(R52<10,"Amber","Red")) -> Green | T52: =IF(N52="Settled","None",IF(C52-Config!$B$1<=0,"Overdue",IF(C52-Config!$B$1<=1,"Critical",IF(C52-Config!$B$1<=3,"High","Low")))) -> None | U52: =IF(R52=0,"",RANK(R52,$R$5:$R$104,0))
A53: TRD-049 | B53: 45690 | C53: 45691 | D53: Fixed Income | E53: 7.30% GOI 2053 | F53: IN002023Y456 | G53: INR | H53: 10000 | I53: 99.15 | J53: =H53*I53 -> 991500 | K53: Angel One | L53: Motilal Oswal | M53: S7 Settlement | N53: Settled | P53: =Config!$B$1-B53 -> 491 | Q53: =IFERROR(INDEX('Failure Reference'!$C$4:$C$9,MATCH(O53,'Failure Reference'!$A$4:$A$9,0)),0) -> 0 | R53: =IF(N53="Settled",0,Q53+P53*0.5+IFERROR(INDEX(Config!$B$4:$B$7,MATCH(D53,Config!$A$4:$A$7,0)),1)+IF(C53-Config!$B$1<=1,5,0)) -> 0 | S53: =IF(R53=0,"Green",IF(R53<10,"Amber","Red")) -> Green | T53: =IF(N53="Settled","None",IF(C53-Config!$B$1<=0,"Overdue",IF(C53-Config!$B$1<=1,"Critical",IF(C53-Config!$B$1<=3,"High","Low")))) -> None | U53: =IF(R53=0,"",RANK(R53,$R$5:$R$104,0))
A54: TRD-050 | B54: 45815 | C54: 45816 | D54: Derivatives | E54: EURINR Futures | F54: N/A | G54: INR | H54: 5 | I54: 89.74 | J54: =H54*I54 -> 448.7 | K54: HDFC Securities | L54: Sharekhan | M54: S7 Settlement | N54: Settled | P54: =Config!$B$1-B54 -> 366 | Q54: =IFERROR(INDEX('Failure Reference'!$C$4:$C$9,MATCH(O54,'Failure Reference'!$A$4:$A$9,0)),0) -> 0 | R54: =IF(N54="Settled",0,Q54+P54*0.5+IFERROR(INDEX(Config!$B$4:$B$7,MATCH(D54,Config!$A$4:$A$7,0)),1)+IF(C54-Config!$B$1<=1,5,0)) -> 0 | S54: =IF(R54=0,"Green",IF(R54<10,"Amber","Red")) -> Green | T54: =IF(N54="Settled","None",IF(C54-Config!$B$1<=0,"Overdue",IF(C54-Config!$B$1<=1,"Critical",IF(C54-Config!$B$1<=3,"High","Low")))) -> None | U54: =IF(R54=0,"",RANK(R54,$R$5:$R$104,0))
A55: TRD-051 | B55: 45731 | C55: 45732 | D55: Fixed Income | E55: 7.30% GOI 2053 | F55: IN002023Y456 | G55: INR | H55: 10000 | I55: 99.63 | J55: =H55*I55 -> 996300 | K55: Nuvama Wealth | L55: Sharekhan | M55: S4 Allocation | N55: Break | O55: Allocation Error | P55: =Config!$B$1-B55 -> 450 | Q55: =IFERROR(INDEX('Failure Reference'!$C$4:$C$9,MATCH(O55,'Failure Reference'!$A$4:$A$9,0)),0) -> 7 | R55: =IF(N55="Settled",0,Q55+P55*0.5+IFERROR(INDEX(Config!$B$4:$B$7,MATCH(D55,Config!$A$4:$A$7,0)),1)+IF(C55-Config!$B$1<=1,5,0)) -> 238.5 | S55: =IF(R55=0,"Green",IF(R55<10,"Amber","Red")) -> Red | T55: =IF(N55="Settled","None",IF(C55-Config!$B$1<=0,"Overdue",IF(C55-Config!$B$1<=1,"Critical",IF(C55-Config!$B$1<=3,"High","Low")))) -> Overdue | U55: =IF(R55=0,"",RANK(R55,$R$5:$R$104,0)) -> 12
A56: TRD-052 | B56: 45777 | C56: 45778 | D56: Derivatives | E56: USDINR Futures | F56: N/A | G56: INR | H56: 10 | I56: 84.38 | J56: =H56*I56 -> 843.8 | K56: JM Financial | L56: IIFL Securities | M56: S7 Settlement | N56: Settled | P56: =Config!$B$1-B56 -> 404 | Q56: =IFERROR(INDEX('Failure Reference'!$C$4:$C$9,MATCH(O56,'Failure Reference'!$A$4:$A$9,0)),0) -> 0 | R56: =IF(N56="Settled",0,Q56+P56*0.5+IFERROR(INDEX(Config!$B$4:$B$7,MATCH(D56,Config!$A$4:$A$7,0)),1)+IF(C56-Config!$B$1<=1,5,0)) -> 0 | S56: =IF(R56=0,"Green",IF(R56<10,"Amber","Red")) -> Green | T56: =IF(N56="Settled","None",IF(C56-Config!$B$1<=0,"Overdue",IF(C56-Config!$B$1<=1,"Critical",IF(C56-Config!$B$1<=3,"High","Low")))) -> None | U56: =IF(R56=0,"",RANK(R56,$R$5:$R$104,0))
A57: TRD-053 | B57: 45701 | C57: 45702 | D57: Commodities | E57: Gold Futures (MCX) | F57: N/A | G57: USD | H57: 50 | I57: 72656.84 | J57: =H57*I57 -> 3632842 | K57: ICICI Securities | L57: Axis Securities | M57: S7 Settlement | N57: Settled | P57: =Config!$B$1-B57 -> 480 | Q57: =IFERROR(INDEX('Failure Reference'!$C$4:$C$9,MATCH(O57,'Failure Reference'!$A$4:$A$9,0)),0) -> 0 | R57: =IF(N57="Settled",0,Q57+P57*0.5+IFERROR(INDEX(Config!$B$4:$B$7,MATCH(D57,Config!$A$4:$A$7,0)),1)+IF(C57-Config!$B$1<=1,5,0)) -> 0 | S57: =IF(R57=0,"Green",IF(R57<10,"Amber","Red")) -> Green | T57: =IF(N57="Settled","None",IF(C57-Config!$B$1<=0,"Overdue",IF(C57-Config!$B$1<=1,"Critical",IF(C57-Config!$B$1<=3,"High","Low")))) -> None | U57: =IF(R57=0,"",RANK(R57,$R$5:$R$104,0))
A58: TRD-054 | B58: 45830 | C58: 45831 | D58: Derivatives | E58: Reliance Futures | F58: N/A | G58: INR | H58: 2 | I58: 2902.42 | J58: =H58*I58 -> 5804.84 | K58: Motilal Oswal | L58: HDFC Securities | M58: S7 Settlement | N58: Settled | P58: =Config!$B$1-B58 -> 351 | Q58: =IFERROR(INDEX('Failure Reference'!$C$4:$C$9,MATCH(O58,'Failure Reference'!$A$4:$A$9,0)),0) -> 0 | R58: =IF(N58="Settled",0,Q58+P58*0.5+IFERROR(INDEX(Config!$B$4:$B$7,MATCH(D58,Config!$A$4:$A$7,0)),1)+IF(C58-Config!$B$1<=1,5,0)) -> 0 | S58: =IF(R58=0,"Green",IF(R58<10,"Amber","Red")) -> Green | T58: =IF(N58="Settled","None",IF(C58-Config!$B$1<=0,"Overdue",IF(C58-Config!$B$1<=1,"Critical",IF(C58-Config!$B$1<=3,"High","Low")))) -> None | U58: =IF(R58=0,"",RANK(R58,$R$5:$R$104,0))
A59: TRD-055 | B59: 45669 | C59: 45670 | D59: Commodities | E59: Silver Futures (MCX) | F59: N/A | G59: INR | H59: 100 | I59: 88863.11 | J59: =H59*I59 -> 8886311 | K59: IIFL Securities | L59: Angel One | M59: S7 Settlement | N59: Settled | P59: =Config!$B$1-B59 -> 512 | Q59: =IFERROR(INDEX('Failure Reference'!$C$4:$C$9,MATCH(O59,'Failure Reference'!$A$4:$A$9,0)),0) -> 0 | R59: =IF(N59="Settled",0,Q59+P59*0.5+IFERROR(INDEX(Config!$B$4:$B$7,MATCH(D59,Config!$A$4:$A$7,0)),1)+IF(C59-Config!$B$1<=1,5,0)) -> 0 | S59: =IF(R59=0,"Green",IF(R59<10,"Amber","Red")) -> Green | T59: =IF(N59="Settled","None",IF(C59-Config!$B$1<=0,"Overdue",IF(C59-Config!$B$1<=1,"Critical",IF(C59-Config!$B$1<=3,"High","Low")))) -> None | U59: =IF(R59=0,"",RANK(R59,$R$5:$R$104,0))
A60: TRD-056 | B60: 45819 | C60: 45820 | D60: Commodities | E60: Copper Futures (MCX) | F60: N/A | G60: USD | H60: 25 | I60: 4.38 | J60: =H60*I60 -> 109.5 | K60: IIFL Securities | L60: Angel One | M60: S7 Settlement | N60: Settled | P60: =Config!$B$1-B60 -> 362 | Q60: =IFERROR(INDEX('Failure Reference'!$C$4:$C$9,MATCH(O60,'Failure Reference'!$A$4:$A$9,0)),0) -> 0 | R60: =IF(N60="Settled",0,Q60+P60*0.5+IFERROR(INDEX(Config!$B$4:$B$7,MATCH(D60,Config!$A$4:$A$7,0)),1)+IF(C60-Config!$B$1<=1,5,0)) -> 0 | S60: =IF(R60=0,"Green",IF(R60<10,"Amber","Red")) -> Green | T60: =IF(N60="Settled","None",IF(C60-Config!$B$1<=0,"Overdue",IF(C60-Config!$B$1<=1,"Critical",IF(C60-Config!$B$1<=3,"High","Low")))) -> None | U60: =IF(R60=0,"",RANK(R60,$R$5:$R$104,0))
A61: TRD-057 | B61: 45720 | C61: 45721 | D61: Equity | E61: HDFC Bank Ltd | F61: INE040A01034 | G61: INR | H61: 1000 | I61: 1706.43 | J61: =H61*I61 -> 1706430 | K61: ICICI Securities | L61: IIFL Securities | M61: S7 Settlement | N61: Settled | P61: =Config!$B$1-B61 -> 461 | Q61: =IFERROR(INDEX('Failure Reference'!$C$4:$C$9,MATCH(O61,'Failure Reference'!$A$4:$A$9,0)),0) -> 0 | R61: =IF(N61="Settled",0,Q61+P61*0.5+IFERROR(INDEX(Config!$B$4:$B$7,MATCH(D61,Config!$A$4:$A$7,0)),1)+IF(C61-Config!$B$1<=1,5,0)) -> 0 | S61: =IF(R61=0,"Green",IF(R61<10,"Amber","Red")) -> Green | T61: =IF(N61="Settled","None",IF(C61-Config!$B$1<=0,"Overdue",IF(C61-Config!$B$1<=1,"Critical",IF(C61-Config!$B$1<=3,"High","Low")))) -> None | U61: =IF(R61=0,"",RANK(R61,$R$5:$R$104,0))
A62: TRD-058 | B62: 45714 | C62: 45715 | D62: Derivatives | E62: Bank Nifty Futures | F62: N/A | G62: INR | H62: 50 | I62: 48251.93 | J62: =H62*I62 -> 2412596.5 | K62: HDFC Securities | L62: Nuvama Wealth | M62: S7 Settlement | N62: Settled | P62: =Config!$B$1-B62 -> 467 | Q62: =IFERROR(INDEX('Failure Reference'!$C$4:$C$9,MATCH(O62,'Failure Reference'!$A$4:$A$9,0)),0) -> 0 | R62: =IF(N62="Settled",0,Q62+P62*0.5+IFERROR(INDEX(Config!$B$4:$B$7,MATCH(D62,Config!$A$4:$A$7,0)),1)+IF(C62-Config!$B$1<=1,5,0)) -> 0 | S62: =IF(R62=0,"Green",IF(R62<10,"Amber","Red")) -> Green | T62: =IF(N62="Settled","None",IF(C62-Config!$B$1<=0,"Overdue",IF(C62-Config!$B$1<=1,"Critical",IF(C62-Config!$B$1<=3,"High","Low")))) -> None | U62: =IF(R62=0,"",RANK(R62,$R$5:$R$104,0))
A63: TRD-059 | B63: 45721 | C63: 45722 | D63: Fixed Income | E63: HDFC Ltd Corp Bond | F63: INE001A08145 | G63: INR | H63: 1000 | I63: 101.62 | J63: =H63*I63 -> 101620 | K63: IIFL Securities | L63: Nuvama Wealth | M63: S7 Settlement | N63: Settled | P63: =Config!$B$1-B63 -> 460 | Q63: =IFERROR(INDEX('Failure Reference'!$C$4:$C$9,MATCH(O63,'Failure Reference'!$A$4:$A$9,0)),0) -> 0 | R63: =IF(N63="Settled",0,Q63+P63*0.5+IFERROR(INDEX(Config!$B$4:$B$7,MATCH(D63,Config!$A$4:$A$7,0)),1)+IF(C63-Config!$B$1<=1,5,0)) -> 0 | S63: =IF(R63=0,"Green",IF(R63<10,"Amber","Red")) -> Green | T63: =IF(N63="Settled","None",IF(C63-Config!$B$1<=0,"Overdue",IF(C63-Config!$B$1<=1,"Critical",IF(C63-Config!$B$1<=3,"High","Low")))) -> None | U63: =IF(R63=0,"",RANK(R63,$R$5:$R$104,0))
A64: TRD-060 | B64: 45801 | C64: 45802 | D64: Commodities | E64: Copper Futures (MCX) | F64: N/A | G64: USD | H64: 50 | I64: 4.52 | J64: =H64*I64 -> 226 | K64: Nuvama Wealth | L64: JM Financial | M64: S7 Settlement | N64: Settled | P64: =Config!$B$1-B64 -> 380 | Q64: =IFERROR(INDEX('Failure Reference'!$C$4:$C$9,MATCH(O64,'Failure Reference'!$A$4:$A$9,0)),0) -> 0 | R64: =IF(N64="Settled",0,Q64+P64*0.5+IFERROR(INDEX(Config!$B$4:$B$7,MATCH(D64,Config!$A$4:$A$7,0)),1)+IF(C64-Config!$B$1<=1,5,0)) -> 0 | S64: =IF(R64=0,"Green",IF(R64<10,"Amber","Red")) -> Green | T64: =IF(N64="Settled","None",IF(C64-Config!$B$1<=0,"Overdue",IF(C64-Config!$B$1<=1,"Critical",IF(C64-Config!$B$1<=3,"High","Low")))) -> None | U64: =IF(R64=0,"",RANK(R64,$R$5:$R$104,0))
A65: TRD-061 | B65: 45767 | C65: 45768 | D65: Equity | E65: Wipro Ltd | F65: INE075A01022 | G65: INR | H65: 750 | I65: 472.43 | J65: =H65*I65 -> 354322.5 | K65: Motilal Oswal | L65: JM Financial | M65: S7 Settlement | N65: Settled | P65: =Config!$B$1-B65 -> 414 | Q65: =IFERROR(INDEX('Failure Reference'!$C$4:$C$9,MATCH(O65,'Failure Reference'!$A$4:$A$9,0)),0) -> 0 | R65: =IF(N65="Settled",0,Q65+P65*0.5+IFERROR(INDEX(Config!$B$4:$B$7,MATCH(D65,Config!$A$4:$A$7,0)),1)+IF(C65-Config!$B$1<=1,5,0)) -> 0 | S65: =IF(R65=0,"Green",IF(R65<10,"Amber","Red")) -> Green | T65: =IF(N65="Settled","None",IF(C65-Config!$B$1<=0,"Overdue",IF(C65-Config!$B$1<=1,"Critical",IF(C65-Config!$B$1<=3,"High","Low")))) -> None | U65: =IF(R65=0,"",RANK(R65,$R$5:$R$104,0))
A66: TRD-062 | B66: 45773 | C66: 45774 | D66: Equity | E66: ICICI Bank Ltd | F66: INE090A01021 | G66: INR | H66: 1500 | I66: 1091.69 | J66: =H66*I66 -> 1637535 | K66: Axis Securities | L66: Nuvama Wealth | M66: S7 Settlement | N66: Settled | P66: =Config!$B$1-B66 -> 408 | Q66: =IFERROR(INDEX('Failure Reference'!$C$4:$C$9,MATCH(O66,'Failure Reference'!$A$4:$A$9,0)),0) -> 0 | R66: =IF(N66="Settled",0,Q66+P66*0.5+IFERROR(INDEX(Config!$B$4:$B$7,MATCH(D66,Config!$A$4:$A$7,0)),1)+IF(C66-Config!$B$1<=1,5,0)) -> 0 | S66: =IF(R66=0,"Green",IF(R66<10,"Amber","Red")) -> Green | T66: =IF(N66="Settled","None",IF(C66-Config!$B$1<=0,"Overdue",IF(C66-Config!$B$1<=1,"Critical",IF(C66-Config!$B$1<=3,"High","Low")))) -> None | U66: =IF(R66=0,"",RANK(R66,$R$5:$R$104,0))
A67: TRD-063 | B67: 45782 | C67: 45783 | D67: Equity | E67: Bajaj Finance Ltd | F67: INE296A01024 | G67: INR | H67: 200 | I67: 6964.4 | J67: =H67*I67 -> 1392880 | K67: ICICI Securities | L67: Sharekhan | M67: S7 Settlement | N67: Settled | P67: =Config!$B$1-B67 -> 399 | Q67: =IFERROR(INDEX('Failure Reference'!$C$4:$C$9,MATCH(O67,'Failure Reference'!$A$4:$A$9,0)),0) -> 0 | R67: =IF(N67="Settled",0,Q67+P67*0.5+IFERROR(INDEX(Config!$B$4:$B$7,MATCH(D67,Config!$A$4:$A$7,0)),1)+IF(C67-Config!$B$1<=1,5,0)) -> 0 | S67: =IF(R67=0,"Green",IF(R67<10,"Amber","Red")) -> Green | T67: =IF(N67="Settled","None",IF(C67-Config!$B$1<=0,"Overdue",IF(C67-Config!$B$1<=1,"Critical",IF(C67-Config!$B$1<=3,"High","Low")))) -> None | U67: =IF(R67=0,"",RANK(R67,$R$5:$R$104,0))
... A72: TRD-068 | B72: 45659 | C72: 45660 | D72: Equity | E72: State Bank of India | F72: INE062A01020 | G72: INR | H72: 300 | I72: 779.26 | J72: =H72*I72 -> 233778 | K72: Angel One | L72: Nuvama Wealth | M72: S7 Settlement | N72: Settled | P72: =Config!$B$1-B72 -> 522 | Q72: =IFERROR(INDEX('Failure Reference'!$C$4:$C$9,MATCH(O72,'Failure Reference'!$A$4:$A$9,0)),0) -> 0 | R72: =IF(N72="Settled",0,Q72+P72*0.5+IFERROR(INDEX(Config!$B$4:$B$7,MATCH(D72,Config!$A$4:$A$7,0)),1)+IF(C72-Config!$B$1<=1,5,0)) -> 0 | S72: =IF(R72=0,"Green",IF(R72<10,"Amber","Red")) -> Green | T72: =IF(N72="Settled","None",IF(C72-Config!$B$1<=0,"Overdue",IF(C72-Config!$B$1<=1,"Critical",IF(C72-Config!$B$1<=3,"High","Low")))) -> None | U72: =IF(R72=0,"",RANK(R72,$R$5:$R$104,0))
A73: TRD-069 | B73: 45797 | C73: 45798 | D73: Derivatives | E73: EURINR Futures | F73: N/A | G73: INR | H73: 2 | I73: 90.19 | J73: =H73*I73 -> 180.38 | K73: Axis Securities | L73: IIFL Securities | M73: S2 Enrichment | N73: Break | O73: SSI Error | P73: =Config!$B$1-B73 -> 384 | Q73: =IFERROR(INDEX('Failure Reference'!$C$4:$C$9,MATCH(O73,'Failure Reference'!$A$4:$A$9,0)),0) -> 6 | R73: =IF(N73="Settled",0,Q73+P73*0.5+IFERROR(INDEX(Config!$B$4:$B$7,MATCH(D73,Config!$A$4:$A$7,0)),1)+IF(C73-Config!$B$1<=1,5,0)) -> 205 | S73: =IF(R73=0,"Green",IF(R73<10,"Amber","Red")) -> Red | T73: =IF(N73="Settled","None",IF(C73-Config!$B$1<=0,"Overdue",IF(C73-Config!$B$1<=1,"Critical",IF(C73-Config!$B$1<=3,"High","Low")))) -> Overdue | U73: =IF(R73=0,"",RANK(R73,$R$5:$R$104,0)) -> 21
A74: TRD-070 | B74: 45782 | C74: 45783 | D74: Equity | E74: Reliance Industries Ltd | F74: INE002A01018 | G74: INR | H74: 500 | I74: 2803.3 | J74: =H74*I74 -> 1401650 | K74: Angel One | L74: Motilal Oswal | M74: S7 Settlement | N74: Settled | P74: =Config!$B$1-B74 -> 399 | Q74: =IFERROR(INDEX('Failure Reference'!$C$4:$C$9,MATCH(O74,'Failure Reference'!$A$4:$A$9,0)),0) -> 0 | R74: =IF(N74="Settled",0,Q74+P74*0.5+IFERROR(INDEX(Config!$B$4:$B$7,MATCH(D74,Config!$A$4:$A$7,0)),1)+IF(C74-Config!$B$1<=1,5,0)) -> 0 | S74: =IF(R74=0,"Green",IF(R74<10,"Amber","Red")) -> Green | T74: =IF(N74="Settled","None",IF(C74-Config!$B$1<=0,"Overdue",IF(C74-Config!$B$1<=1,"Critical",IF(C74-Config!$B$1<=3,"High","Low")))) -> None | U74: =IF(R74=0,"",RANK(R74,$R$5:$R$104,0))
A75: TRD-071 | B75: 45777 | C75: 45778 | D75: Derivatives | E75: Bank Nifty Futures | F75: N/A | G75: INR | H75: 20 | I75: 48298.69 | J75: =H75*I75 -> 965973.8 | K75: Angel One | L75: HDFC Securities | M75: S7 Settlement | N75: Settled | P75: =Config!$B$1-B75 -> 404 | Q75: =IFERROR(INDEX('Failure Reference'!$C$4:$C$9,MATCH(O75,'Failure Reference'!$A$4:$A$9,0)),0) -> 0 | R75: =IF(N75="Settled",0,Q75+P75*0.5+IFERROR(INDEX(Config!$B$4:$B$7,MATCH(D75,Config!$A$4:$A$7,0)),1)+IF(C75-Config!$B$1<=1,5,0)) -> 0 | S75: =IF(R75=0,"Green",IF(R75<10,"Amber","Red")) -> Green | T75: =IF(N75="Settled","None",IF(C75-Config!$B$1<=0,"Overdue",IF(C75-Config!$B$1<=1,"Critical",IF(C75-Config!$B$1<=3,"High","Low")))) -> None | U75: =IF(R75=0,"",RANK(R75,$R$5:$R$104,0))
A76: TRD-072 | B76: 45679 | C76: 45680 | D76: Equity | E76: Bajaj Finance Ltd | F76: INE296A01024 | G76: INR | H76: 500 | I76: 6865.44 | J76: =H76*I76 -> 3432720 | K76: IIFL Securities | L76: Motilal Oswal | M76: S0 Trade Capture | N76: Break | O76: Trade Capture Error | P76: =Config!$B$1-B76 -> 502 | Q76: =IFERROR(INDEX('Failure Reference'!$C$4:$C$9,MATCH(O76,'Failure Reference'!$A$4:$A$9,0)),0) -> 5 | R76: =IF(N76="Settled",0,Q76+P76*0.5+IFERROR(INDEX(Config!$B$4:$B$7,MATCH(D76,Config!$A$4:$A$7,0)),1)+IF(C76-Config!$B$1<=1,5,0)) -> 262 | S76: =IF(R76=0,"Green",IF(R76<10,"Amber","Red")) -> Red | T76: =IF(N76="Settled","None",IF(C76-Config!$B$1<=0,"Overdue",IF(C76-Config!$B$1<=1,"Critical",IF(C76-Config!$B$1<=3,"High","Low")))) -> Overdue | U76: =IF(R76=0,"",RANK(R76,$R$5:$R$104,0)) -> 3
A77: TRD-073 | B77: 45670 | C77: 45671 | D77: Derivatives | E77: Reliance Futures | F77: N/A | G77: INR | H77: 10 | I77: 2820.48 | J77: =H77*I77 -> 28204.8 | K77: IIFL Securities | L77: Sharekhan | M77: S7 Settlement | N77: Settled | P77: =Config!$B$1-B77 -> 511 | Q77: =IFERROR(INDEX('Failure Reference'!$C$4:$C$9,MATCH(O77,'Failure Reference'!$A$4:$A$9,0)),0) -> 0 | R77: =IF(N77="Settled",0,Q77+P77*0.5+IFERROR(INDEX(Config!$B$4:$B$7,MATCH(D77,Config!$A$4:$A$7,0)),1)+IF(C77-Config!$B$1<=1,5,0)) -> 0 | S77: =IF(R77=0,"Green",IF(R77<10,"Amber","Red")) -> Green | T77: =IF(N77="Settled","None",IF(C77-Config!$B$1<=0,"Overdue",IF(C77-Config!$B$1<=1,"Critical",IF(C77-Config!$B$1<=3,"High","Low")))) -> None | U77: =IF(R77=0,"",RANK(R77,$R$5:$R$104,0))
A78: TRD-074 | B78: 45744 | C78: 45745 | D78: Fixed Income | E78: HDFC Ltd Corp Bond | F78: INE001A08145 | G78: INR | H78: 10000 | I78: 100.9 | J78: =H78*I78 -> 1009000 | K78: Angel One | L78: Axis Securities | M78: S7 Settlement | N78: Break | O78: Corporate Action Impact | P78: =Config!$B$1-B78 -> 437 | Q78: =IFERROR(INDEX('Failure Reference'!$C$4:$C$9,MATCH(O78,'Failure Reference'!$A$4:$A$9,0)),0) -> 4 | R78: =IF(N78="Settled",0,Q78+P78*0.5+IFERROR(INDEX(Config!$B$4:$B$7,MATCH(D78,Config!$A$4:$A$7,0)),1)+IF(C78-Config!$B$1<=1,5,0)) -> 229 | S78: =IF(R78=0,"Green",IF(R78<10,"Amber","Red")) -> Red | T78: =IF(N78="Settled","None",IF(C78-Config!$B$1<=0,"Overdue",IF(C78-Config!$B$1<=1,"Critical",IF(C78-Config!$B$1<=3,"High","Low")))) -> Overdue | U78: =IF(R78=0,"",RANK(R78,$R$5:$R$104,0)) -> 15
A79: TRD-075 | B79: 45678 | C79: 45679 | D79: Fixed Income | E79: T-Bill 91D | F79: IN002024T001 | G79: INR | H79: 1000 | I79: 100.49 | J79: =H79*I79 -> 100490 | K79: HDFC Securities | L79: Angel One | M79: S7 Settlement | N79: Settled | P79: =Config!$B$1-B79 -> 503 | Q79: =IFERROR(INDEX('Failure Reference'!$C$4:$C$9,MATCH(O79,'Failure Reference'!$A$4:$A$9,0)),0) -> 0 | R79: =IF(N79="Settled",0,Q79+P79*0.5+IFERROR(INDEX(Config!$B$4:$B$7,MATCH(D79,Config!$A$4:$A$7,0)),1)+IF(C79-Config!$B$1<=1,5,0)) -> 0 | S79: =IF(R79=0,"Green",IF(R79<10,"Amber","Red")) -> Green | T79: =IF(N79="Settled","None",IF(C79-Config!$B$1<=0,"Overdue",IF(C79-Config!$B$1<=1,"Critical",IF(C79-Config!$B$1<=3,"High","Low")))) -> None | U79: =IF(R79=0,"",RANK(R79,$R$5:$R$104,0))
A80: TRD-076 | B80: 45715 | C80: 45716 | D80: Fixed Income | E80: Tata Steel Corp Bond | F80: INE081A08123 | G80: INR | H80: 1000 | I80: 103.45 | J80: =H80*I80 -> 103450 | K80: HDFC Securities | L80: ICICI Securities | M80: S1 Validation | N80: In Progress | P80: =Config!$B$1-B80 -> 466 | Q80: =IFERROR(INDEX('Failure Reference'!$C$4:$C$9,MATCH(O80,'Failure Reference'!$A$4:$A$9,0)),0) -> 0 | R80: =IF(N80="Settled",0,Q80+P80*0.5+IFERROR(INDEX(Config!$B$4:$B$7,MATCH(D80,Config!$A$4:$A$7,0)),1)+IF(C80-Config!$B$1<=1,5,0)) -> 239.5 | S80: =IF(R80=0,"Green",IF(R80<10,"Amber","Red")) -> Red | T80: =IF(N80="Settled","None",IF(C80-Config!$B$1<=0,"Overdue",IF(C80-Config!$B$1<=1,"Critical",IF(C80-Config!$B$1<=3,"High","Low")))) -> Overdue | U80: =IF(R80=0,"",RANK(R80,$R$5:$R$104,0)) -> 11
A81: TRD-077 | B81: 45709 | C81: 45710 | D81: Equity | E81: Wipro Ltd | F81: INE075A01022 | G81: INR | H81: 100 | I81: 480.76 | J81: =H81*I81 -> 48076 | K81: Kotak Securities | L81: Motilal Oswal | M81: S7 Settlement | N81: Settled | P81: =Config!$B$1-B81 -> 472 | Q81: =IFERROR(INDEX('Failure Reference'!$C$4:$C$9,MATCH(O81,'Failure Reference'!$A$4:$A$9,0)),0) -> 0 | R81: =IF(N81="Settled",0,Q81+P81*0.5+IFERROR(INDEX(Config!$B$4:$B$7,MATCH(D81,Config!$A$4:$A$7,0)),1)+IF(C81-Config!$B$1<=1,5,0)) -> 0 | S81: =IF(R81=0,"Green",IF(R81<10,"Amber","Red")) -> Green | T81: =IF(N81="Settled","None",IF(C81-Config!$B$1<=0,"Overdue",IF(C81-Config!$B$1<=1,"Critical",IF(C81-Config!$B$1<=3,"High","Low")))) -> None | U81: =IF(R81=0,"",RANK(R81,$R$5:$R$104,0))
A82: TRD-078 | B82: 45779 | C82: 45780 | D82: Derivatives | E82: Nifty 50 Futures | F82: N/A | G82: INR | H82: 20 | I82: 23053.13 | J82: =H82*I82 -> 461062.6 | K82: IIFL Securities | L82: Axis Securities | M82: S7 Settlement | N82: Settled | P82: =Config!$B$1-B82 -> 402 | Q82: =IFERROR(INDEX('Failure Reference'!$C$4:$C$9,MATCH(O82,'Failure Reference'!$A$4:$A$9,0)),0) -> 0 | R82: =IF(N82="Settled",0,Q82+P82*0.5+IFERROR(INDEX(Config!$B$4:$B$7,MATCH(D82,Config!$A$4:$A$7,0)),1)+IF(C82-Config!$B$1<=1,5,0)) -> 0 | S82: =IF(R82=0,"Green",IF(R82<10,"Amber","Red")) -> Green | T82: =IF(N82="Settled","None",IF(C82-Config!$B$1<=0,"Overdue",IF(C82-Config!$B$1<=1,"Critical",IF(C82-Config!$B$1<=3,"High","Low")))) -> None | U82: =IF(R82=0,"",RANK(R82,$R$5:$R$104,0))
A83: TRD-079 | B83: 45752 | C83: 45753 | D83: Commodities | E83: Silver Futures (MCX) | F83: N/A | G83: INR | H83: 200 | I83: 88813.78 | J83: =H83*I83 -> 17762756 | K83: Motilal Oswal | L83: Sharekhan | M83: S0 Trade Capture | N83: In Progress | P83: =Config!$B$1-B83 -> 429 | Q83: =IFERROR(INDEX('Failure Reference'!$C$4:$C$9,MATCH(O83,'Failure Reference'!$A$4:$A$9,0)),0) -> 0 | R83: =IF(N83="Settled",0,Q83+P83*0.5+IFERROR(INDEX(Config!$B$4:$B$7,MATCH(D83,Config!$A$4:$A$7,0)),1)+IF(C83-Config!$B$1<=1,5,0)) -> 222 | S83: =IF(R83=0,"Green",IF(R83<10,"Amber","Red")) -> Red | T83: =IF(N83="Settled","None",IF(C83-Config!$B$1<=0,"Overdue",IF(C83-Config!$B$1<=1,"Critical",IF(C83-Config!$B$1<=3,"High","Low")))) -> Overdue | U83: =IF(R83=0,"",RANK(R83,$R$5:$R$104,0)) -> 18
A84: TRD-080 | B84: 45806 | C84: 45807 | D84: Equity | E84: Reliance Industries Ltd | F84: INE002A01018 | G84: INR | H84: 300 | I84: 2871.6 | J84: =H84*I84 -> 861480 | K84: Angel One | L84: IIFL Securities | M84: S5 Matching | N84: In Progress | P84: =Config!$B$1-B84 -> 375 | Q84: =IFERROR(INDEX('Failure Reference'!$C$4:$C$9,MATCH(O84,'Failure Reference'!$A$4:$A$9,0)),0) -> 0 | R84: =IF(N84="Settled",0,Q84+P84*0.5+IFERROR(INDEX(Config!$B$4:$B$7,MATCH(D84,Config!$A$4:$A$7,0)),1)+IF(C84-Config!$B$1<=1,5,0)) -> 193.5 | S84: =IF(R84=0,"Green",IF(R84<10,"Amber","Red")) -> Red | T84: =IF(N84="Settled","None",IF(C84-Config!$B$1<=0,"Overdue",IF(C84-Config!$B$1<=1,"Critical",IF(C84-Config!$B$1<=3,"High","Low")))) -> Overdue | U84: =IF(R84=0,"",RANK(R84,$R$5:$R$104,0)) -> 23
A85: TRD-081 | B85: 45708 | C85: 45709 | D85: Derivatives | E85: Nifty 50 Futures | F85: N/A | G85: INR | H85: 20 | I85: 22706.76 | J85: =H85*I85 -> 454135.2 | K85: Kotak Securities | L85: ICICI Securities | M85: S7 Settlement | N85: Settled | P85: =Config!$B$1-B85 -> 473 | Q85: =IFERROR(INDEX('Failure Reference'!$C$4:$C$9,MATCH(O85,'Failure Reference'!$A$4:$A$9,0)),0) -> 0 | R85: =IF(N85="Settled",0,Q85+P85*0.5+IFERROR(INDEX(Config!$B$4:$B$7,MATCH(D85,Config!$A$4:$A$7,0)),1)+IF(C85-Config!$B$1<=1,5,0)) -> 0 | S85: =IF(R85=0,"Green",IF(R85<10,"Amber","Red")) -> Green | T85: =IF(N85="Settled","None",IF(C85-Config!$B$1<=0,"Overdue",IF(C85-Config!$B$1<=1,"Critical",IF(C85-Config!$B$1<=3,"High","Low")))) -> None | U85: =IF(R85=0,"",RANK(R85,$R$5:$R$104,0))
A86: TRD-082 | B86: 45836 | C86: 45837 | D86: Equity | E86: Asian Paints Ltd | F86: INE021A01026 | G86: INR | H86: 300 | I86: 2991.23 | J86: =H86*I86 -> 897369 | K86: Nuvama Wealth | L86: ICICI Securities | M86: S7 Settlement | N86: Settled | P86: =Config!$B$1-B86 -> 345 | Q86: =IFERROR(INDEX('Failure Reference'!$C$4:$C$9,MATCH(O86,'Failure Reference'!$A$4:$A$9,0)),0) -> 0 | R86: =IF(N86="Settled",0,Q86+P86*0.5+IFERROR(INDEX(Config!$B$4:$B$7,MATCH(D86,Config!$A$4:$A$7,0)),1)+IF(C86-Config!$B$1<=1,5,0)) -> 0 | S86: =IF(R86=0,"Green",IF(R86<10,"Amber","Red")) -> Green | T86: =IF(N86="Settled","None",IF(C86-Config!$B$1<=0,"Overdue",IF(C86-Config!$B$1<=1,"Critical",IF(C86-Config!$B$1<=3,"High","Low")))) -> None | U86: =IF(R86=0,"",RANK(R86,$R$5:$R$104,0))
A87: TRD-083 | B87: 45802 | C87: 45803 | D87: Equity | E87: Asian Paints Ltd | F87: INE021A01026 | G87: INR | H87: 100 | I87: 2845.84 | J87: =H87*I87 -> 284584 | K87: Angel One | L87: Sharekhan | M87: S7 Settlement | N87: Settled | P87: =Config!$B$1-B87 -> 379 | Q87: =IFERROR(INDEX('Failure Reference'!$C$4:$C$9,MATCH(O87,'Failure Reference'!$A$4:$A$9,0)),0) -> 0 | R87: =IF(N87="Settled",0,Q87+P87*0.5+IFERROR(INDEX(Config!$B$4:$B$7,MATCH(D87,Config!$A$4:$A$7,0)),1)+IF(C87-Config!$B$1<=1,5,0)) -> 0 | S87: =IF(R87=0,"Green",IF(R87<10,"Amber","Red")) -> Green | T87: =IF(N87="Settled","None",IF(C87-Config!$B$1<=0,"Overdue",IF(C87-Config!$B$1<=1,"Critical",IF(C87-Config!$B$1<=3,"High","Low")))) -> None | U87: =IF(R87=0,"",RANK(R87,$R$5:$R$104,0))
A88: TRD-084 | B88: 45675 | C88: 45676 | D88: Equity | E88: Hindustan Unilever | F88: INE030A01027 | G88: INR | H88: 1000 | I88: 2411.1 | J88: =H88*I88 -> 2411100 | K88: Angel One | L88: JM Financial | M88: S0 Trade Capture | N88: In Progress | P88: =Config!$B$1-B88 -> 506 | Q88: =IFERROR(INDEX('Failure Reference'!$C$4:$C$9,MATCH(O88,'Failure Reference'!$A$4:$A$9,0)),0) -> 0 | R88: =IF(N88="Settled",0,Q88+P88*0.5+IFERROR(INDEX(Config!$B$4:$B$7,MATCH(D88,Config!$A$4:$A$7,0)),1)+IF(C88-Config!$B$1<=1,5,0)) -> 259 | S88: =IF(R88=0,"Green",IF(R88<10,"Amber","Red")) -> Red | T88: =IF(N88="Settled","None",IF(C88-Config!$B$1<=0,"Overdue",IF(C88-Config!$B$1<=1,"Critical",IF(C88-Config!$B$1<=3,"High","Low")))) -> Overdue | U88: =IF(R88=0,"",RANK(R88,$R$5:$R$104,0)) -> 5
A89: TRD-085 | B89: 45768 | C89: 45769 | D89: Equity | E89: State Bank of India | F89: INE062A01020 | G89: INR | H89: 1000 | I89: 789.76 | J89: =H89*I89 -> 789760 | K89: IIFL Securities | L89: Motilal Oswal | M89: S4 Allocation | N89: Break | O89: Allocation Error | P89: =Config!$B$1-B89 -> 413 | Q89: =IFERROR(INDEX('Failure Reference'!$C$4:$C$9,MATCH(O89,'Failure Reference'!$A$4:$A$9,0)),0) -> 7 | R89: =IF(N89="Settled",0,Q89+P89*0.5+IFERROR(INDEX(Config!$B$4:$B$7,MATCH(D89,Config!$A$4:$A$7,0)),1)+IF(C89-Config!$B$1<=1,5,0)) -> 219.5 | S89: =IF(R89=0,"Green",IF(R89<10,"Amber","Red")) -> Red | T89: =IF(N89="Settled","None",IF(C89-Config!$B$1<=0,"Overdue",IF(C89-Config!$B$1<=1,"Critical",IF(C89-Config!$B$1<=3,"High","Low")))) -> Overdue | U89: =IF(R89=0,"",RANK(R89,$R$5:$R$104,0)) -> 19
A90: TRD-086 | B90: 45769 | C90: 45770 | D90: Fixed Income | E90: 7.30% GOI 2053 | F90: IN002023Y456 | G90: INR | H90: 25000 | I90: 100.33 | J90: =H90*I90 -> 2508250 | K90: Axis Securities | L90: Nuvama Wealth | M90: S7 Settlement | N90: Settled | P90: =Config!$B$1-B90 -> 412 | Q90: =IFERROR(INDEX('Failure Reference'!$C$4:$C$9,MATCH(O90,'Failure Reference'!$A$4:$A$9,0)),0) -> 0 | R90: =IF(N90="Settled",0,Q90+P90*0.5+IFERROR(INDEX(Config!$B$4:$B$7,MATCH(D90,Config!$A$4:$A$7,0)),1)+IF(C90-Config!$B$1<=1,5,0)) -> 0 | S90: =IF(R90=0,"Green",IF(R90<10,"Amber","Red")) -> Green | T90: =IF(N90="Settled","None",IF(C90-Config!$B$1<=0,"Overdue",IF(C90-Config!$B$1<=1,"Critical",IF(C90-Config!$B$1<=3,"High","Low")))) -> None | U90: =IF(R90=0,"",RANK(R90,$R$5:$R$104,0))
A91: TRD-087 | B91: 45781 | C91: 45782 | D91: Derivatives | E91: USDINR Futures | F91: N/A | G91: INR | H91: 10 | I91: 85.13 | J91: =H91*I91 -> 851.3 | K91: Nuvama Wealth | L91: Axis Securities | M91: S7 Settlement | N91: Settled | P91: =Config!$B$1-B91 -> 400 | Q91: =IFERROR(INDEX('Failure Reference'!$C$4:$C$9,MATCH(O91,'Failure Reference'!$A$4:$A$9,0)),0) -> 0 | R91: =IF(N91="Settled",0,Q91+P91*0.5+IFERROR(INDEX(Config!$B$4:$B$7,MATCH(D91,Config!$A$4:$A$7,0)),1)+IF(C91-Config!$B$1<=1,5,0)) -> 0 | S91: =IF(R91=0,"Green",IF(R91<10,"Amber","Red")) -> Green | T91: =IF(N91="Settled","None",IF(C91-Config!$B$1<=0,"Overdue",IF(C91-Config!$B$1<=1,"Critical",IF(C91-Config!$B$1<=3,"High","Low")))) -> None | U91: =IF(R91=0,"",RANK(R91,$R$5:$R$104,0))
A92: TRD-088 | B92: 45740 | C92: 45741 | D92: Commodities | E92: Silver Futures (MCX) | F92: N/A | G92: USD | H92: 10 | I92: 84791.87 | J92: =H92*I92 -> 847918.7 | K92: Kotak Securities | L92: JM Financial | M92: S4 Allocation | N92: In Progress | P92: =Config!$B$1-B92 -> 441 | Q92: =IFERROR(INDEX('Failure Reference'!$C$4:$C$9,MATCH(O92,'Failure Reference'!$A$4:$A$9,0)),0) -> 0 | R92: =IF(N92="Settled",0,Q92+P92*0.5+IFERROR(INDEX(Config!$B$4:$B$7,MATCH(D92,Config!$A$4:$A$7,0)),1)+IF(C92-Config!$B$1<=1,5,0)) -> 228 | S92: =IF(R92=0,"Green",IF(R92<10,"Amber","Red")) -> Red | T92: =IF(N92="Settled","None",IF(C92-Config!$B$1<=0,"Overdue",IF(C92-Config!$B$1<=1,"Critical",IF(C92-Config!$B$1<=3,"High","Low")))) -> Overdue | U92: =IF(R92=0,"",RANK(R92,$R$5:$R$104,0)) -> 17
A93: TRD-089 | B93: 45814 | C93: 45815 | D93: Equity | E93: Bajaj Finance Ltd | F93: INE296A01024 | G93: INR | H93: 500 | I93: 7008.43 | J93: =H93*I93 -> 3504215 | K93: IIFL Securities | L93: Sharekhan | M93: S7 Settlement | N93: Settled | P93: =Config!$B$1-B93 -> 367 | Q93: =IFERROR(INDEX('Failure Reference'!$C$4:$C$9,MATCH(O93,'Failure Reference'!$A$4:$A$9,0)),0) -> 0 | R93: =IF(N93="Settled",0,Q93+P93*0.5+IFERROR(INDEX(Config!$B$4:$B$7,MATCH(D93,Config!$A$4:$A$7,0)),1)+IF(C93-Config!$B$1<=1,5,0)) -> 0 | S93: =IF(R93=0,"Green",IF(R93<10,"Amber","Red")) -> Green | T93: =IF(N93="Settled","None",IF(C93-Config!$B$1<=0,"Overdue",IF(C93-Config!$B$1<=1,"Critical",IF(C93-Config!$B$1<=3,"High","Low")))) -> None | U93: =IF(R93=0,"",RANK(R93,$R$5:$R$104,0))
A94: TRD-090 | B94: 45704 | C94: 45705 | D94: Fixed Income | E94: T-Bill 91D | F94: IN002024T001 | G94: INR | H94: 2000 | I94: 98.92 | J94: =H94*I94 -> 197840 | K94: Axis Securities | L94: Angel One | M94: S7 Settlement | N94: Settled | P94: =Config!$B$1-B94 -> 477 | Q94: =IFERROR(INDEX('Failure Reference'!$C$4:$C$9,MATCH(O94,'Failure Reference'!$A$4:$A$9,0)),0) -> 0 | R94: =IF(N94="Settled",0,Q94+P94*0.5+IFERROR(INDEX(Config!$B$4:$B$7,MATCH(D94,Config!$A$4:$A$7,0)),1)+IF(C94-Config!$B$1<=1,5,0)) -> 0 | S94: =IF(R94=0,"Green",IF(R94<10,"Amber","Red")) -> Green | T94: =IF(N94="Settled","None",IF(C94-Config!$B$1<=0,"Overdue",IF(C94-Config!$B$1<=1,"Critical",IF(C94-Config!$B$1<=3,"High","Low")))) -> None | U94: =IF(R94=0,"",RANK(R94,$R$5:$R$104,0))
A95: TRD-091 | B95: 45729 | C95: 45730 | D95: Fixed Income | E95: T-Bill 182D | F95: IN002024T002 | G95: INR | H95: 5000 | I95: 99.02 | J95: =H95*I95 -> 495100 | K95: JM Financial | L95: Kotak Securities | M95: S0 Trade Capture | N95: In Progress | P95: =Config!$B$1-B95 -> 452 | Q95: =IFERROR(INDEX('Failure Reference'!$C$4:$C$9,MATCH(O95,'Failure Reference'!$A$4:$A$9,0)),0) -> 0 | R95: =IF(N95="Settled",0,Q95+P95*0.5+IFERROR(INDEX(Config!$B$4:$B$7,MATCH(D95,Config!$A$4:$A$7,0)),1)+IF(C95-Config!$B$1<=1,5,0)) -> 232.5 | S95: =IF(R95=0,"Green",IF(R95<10,"Amber","Red")) -> Red | T95: =IF(N95="Settled","None",IF(C95-Config!$B$1<=0,"Overdue",IF(C95-Config!$B$1<=1,"Critical",IF(C95-Config!$B$1<=3,"High","Low")))) -> Overdue | U95: =IF(R95=0,"",RANK(R95,$R$5:$R$104,0)) -> 13
A96: TRD-092 | B96: 45719 | C96: 45720 | D96: Commodities | E96: Natural Gas Futures (MCX) | F96: N/A | G96: INR | H96: 100 | I96: 2.87 | J96: =H96*I96 -> 287 | K96: IIFL Securities | L96: JM Financial | M96: S7 Settlement | N96: Settled | P96: =Config!$B$1-B96 -> 462 | Q96: =IFERROR(INDEX('Failure Reference'!$C$4:$C$9,MATCH(O96,'Failure Reference'!$A$4:$A$9,0)),0) -> 0 | R96: =IF(N96="Settled",0,Q96+P96*0.5+IFERROR(INDEX(Config!$B$4:$B$7,MATCH(D96,Config!$A$4:$A$7,0)),1)+IF(C96-Config!$B$1<=1,5,0)) -> 0 | S96: =IF(R96=0,"Green",IF(R96<10,"Amber","Red")) -> Green | T96: =IF(N96="Settled","None",IF(C96-Config!$B$1<=0,"Overdue",IF(C96-Config!$B$1<=1,"Critical",IF(C96-Config!$B$1<=3,"High","Low")))) -> None | U96: =IF(R96=0,"",RANK(R96,$R$5:$R$104,0))
A97: TRD-093 | B97: 45772 | C97: 45773 | D97: Fixed Income | E97: HDFC Ltd Corp Bond | F97: INE001A08145 | G97: INR | H97: 1000 | I97: 100.14 | J97: =H97*I97 -> 100140 | K97: Kotak Securities | L97: IIFL Securities | M97: S7 Settlement | N97: Settled | P97: =Config!$B$1-B97 -> 409 | Q97: =IFERROR(INDEX('Failure Reference'!$C$4:$C$9,MATCH(O97,'Failure Reference'!$A$4:$A$9,0)),0) -> 0 | R97: =IF(N97="Settled",0,Q97+P97*0.5+IFERROR(INDEX(Config!$B$4:$B$7,MATCH(D97,Config!$A$4:$A$7,0)),1)+IF(C97-Config!$B$1<=1,5,0)) -> 0 | S97: =IF(R97=0,"Green",IF(R97<10,"Amber","Red")) -> Green | T97: =IF(N97="Settled","None",IF(C97-Config!$B$1<=0,"Overdue",IF(C97-Config!$B$1<=1,"Critical",IF(C97-Config!$B$1<=3,"High","Low")))) -> None | U97: =IF(R97=0,"",RANK(R97,$R$5:$R$104,0))
A98: TRD-094 | B98: 45835 | C98: 45836 | D98: Derivatives | E98: Bank Nifty Futures | F98: N/A | G98: INR | H98: 5 | I98: 48674.17 | J98: =H98*I98 -> 243370.85 | K98: Sharekhan | L98: JM Financial | M98: S7 Settlement | N98: Settled | P98: =Config!$B$1-B98 -> 346 | Q98: =IFERROR(INDEX('Failure Reference'!$C$4:$C$9,MATCH(O98,'Failure Reference'!$A$4:$A$9,0)),0) -> 0 | R98: =IF(N98="Settled",0,Q98+P98*0.5+IFERROR(INDEX(Config!$B$4:$B$7,MATCH(D98,Config!$A$4:$A$7,0)),1)+IF(C98-Config!$B$1<=1,5,0)) -> 0 | S98: =IF(R98=0,"Green",IF(R98<10,"Amber","Red")) -> Green | T98: =IF(N98="Settled","None",IF(C98-Config!$B$1<=0,"Overdue",IF(C98-Config!$B$1<=1,"Critical",IF(C98-Config!$B$1<=3,"High","Low")))) -> None | U98: =IF(R98=0,"",RANK(R98,$R$5:$R$104,0))
A99: TRD-095 | B99: 45799 | C99: 45800 | D99: Equity | E99: Hindustan Unilever | F99: INE030A01027 | G99: INR | H99: 300 | I99: 2431.75 | J99: =H99*I99 -> 729525 | K99: JM Financial | L99: Sharekhan | M99: S7 Settlement | N99: Settled | P99: =Config!$B$1-B99 -> 382 | Q99: =IFERROR(INDEX('Failure Reference'!$C$4:$C$9,MATCH(O99,'Failure Reference'!$A$4:$A$9,0)),0) -> 0 | R99: =IF(N99="Settled",0,Q99+P99*0.5+IFERROR(INDEX(Config!$B$4:$B$7,MATCH(D99,Config!$A$4:$A$7,0)),1)+IF(C99-Config!$B$1<=1,5,0)) -> 0 | S99: =IF(R99=0,"Green",IF(R99<10,"Amber","Red")) -> Green | T99: =IF(N99="Settled","None",IF(C99-Config!$B$1<=0,"Overdue",IF(C99-Config!$B$1<=1,"Critical",IF(C99-Config!$B$1<=3,"High","Low")))) -> None | U99: =IF(R99=0,"",RANK(R99,$R$5:$R$104,0))
A100: TRD-096 | B100: 45748 | C100: 45749 | D100: Derivatives | E100: USDINR Futures | F100: N/A | G100: INR | H100: 5 | I100: 82.53 | J100: =H100*I100 -> 412.65 | K100: Kotak Securities | L100: ICICI Securities | M100: S7 Settlement | N100: Settled | P100: =Config!$B$1-B100 -> 433 | Q100: =IFERROR(INDEX('Failure Reference'!$C$4:$C$9,MATCH(O100,'Failure Reference'!$A$4:$A$9,0)),0) -> 0 | R100: =IF(N100="Settled",0,Q100+P100*0.5+IFERROR(INDEX(Config!$B$4:$B$7,MATCH(D100,Config!$A$4:$A$7,0)),1)+IF(C100-Config!$B$1<=1,5,0)) -> 0 | S100: =IF(R100=0,"Green",IF(R100<10,"Amber","Red")) -> Green | T100: =IF(N100="Settled","None",IF(C100-Config!$B$1<=0,"Overdue",IF(C100-Config!$B$1<=1,"Critical",IF(C100-Config!$B$1<=3,"High","Low")))) -> None | U100: =IF(R100=0,"",RANK(R100,$R$5:$R$104,0))
A101: TRD-097 | B101: 45707 | C101: 45708 | D101: Derivatives | E101: Reliance Futures | F101: N/A | G101: INR | H101: 1 | I101: 2891.53 | J101: =H101*I101 -> 2891.53 | K101: Motilal Oswal | L101: Axis Securities | M101: S7 Settlement | N101: Break | O101: Settlement Fail | P101: =Config!$B$1-B101 -> 474 | Q101: =IFERROR(INDEX('Failure Reference'!$C$4:$C$9,MATCH(O101,'Failure Reference'!$A$4:$A$9,0)),0) -> 10 | R101: =IF(N101="Settled",0,Q101+P101*0.5+IFERROR(INDEX(Config!$B$4:$B$7,MATCH(D101,Config!$A$4:$A$7,0)),1)+IF(C101-Config!$B$1<=1,5,0)) -> 254 | S101: =IF(R101=0,"Green",IF(R101<10,"Amber","Red")) -> Red | T101: =IF(N101="Settled","None",IF(C101-Config!$B$1<=0,"Overdue",IF(C101-Config!$B$1<=1,"Critical",IF(C101-Config!$B$1<=3,"High","Low")))) -> Overdue | U101: =IF(R101=0,"",RANK(R101,$R$5:$R$104,0)) -> 7
A102: TRD-098 | B102: 45713 | C102: 45714 | D102: Commodities | E102: Natural Gas Futures (MCX) | F102: N/A | G102: USD | H102: 50 | I102: 2.94 | J102: =H102*I102 -> 147 | K102: ICICI Securities | L102: Axis Securities | M102: S7 Settlement | N102: Settled | P102: =Config!$B$1-B102 -> 468 | Q102: =IFERROR(INDEX('Failure Reference'!$C$4:$C$9,MATCH(O102,'Failure Reference'!$A$4:$A$9,0)),0) -> 0 | R102: =IF(N102="Settled",0,Q102+P102*0.5+IFERROR(INDEX(Config!$B$4:$B$7,MATCH(D102,Config!$A$4:$A$7,0)),1)+IF(C102-Config!$B$1<=1,5,0)) -> 0 | S102: =IF(R102=0,"Green",IF(R102<10,"Amber","Red")) -> Green | T102: =IF(N102="Settled","None",IF(C102-Config!$B$1<=0,"Overdue",IF(C102-Config!$B$1<=1,"Critical",IF(C102-Config!$B$1<=3,"High","Low")))) -> None | U102: =IF(R102=0,"",RANK(R102,$R$5:$R$104,0))
A103: TRD-099 | B103: 45733 | C103: 45734 | D103: Equity | E103: Tata Consultancy Services | F103: INE467B01029 | G103: INR | H103: 300 | I103: 3794.34 | J103: =H103*I103 -> 1138302 | K103: HDFC Securities | L103: Nuvama Wealth | M103: S7 Settlement | N103: Settled | P103: =Config!$B$1-B103 -> 448 | Q103: =IFERROR(INDEX('Failure Reference'!$C$4:$C$9,MATCH(O103,'Failure Reference'!$A$4:$A$9,0)),0) -> 0 | R103: =IF(N103="Settled",0,Q103+P103*0.5+IFERROR(INDEX(Config!$B$4:$B$7,MATCH(D103,Config!$A$4:$A$7,0)),1)+IF(C103-Config!$B$1<=1,5,0)) -> 0 | S103: =IF(R103=0,"Green",IF(R103<10,"Amber","Red")) -> Green | T103: =IF(N103="Settled","None",IF(C103-Config!$B$1<=0,"Overdue",IF(C103-Config!$B$1<=1,"Critical",IF(C103-Config!$B$1<=3,"High","Low")))) -> None | U103: =IF(R103=0,"",RANK(R103,$R$5:$R$104,0))
A104: TRD-100 | B104: 45690 | C104: 45691 | D104: Equity | E104: ICICI Bank Ltd | F104: INE090A01021 | G104: INR | H104: 100 | I104: 1173.12 | J104: =H104*I104 -> 117312 | K104: JM Financial | L104: Axis Securities | M104: S5 Matching | N104: In Progress | P104: =Config!$B$1-B104 -> 491 | Q104: =IFERROR(INDEX('Failure Reference'!$C$4:$C$9,MATCH(O104,'Failure Reference'!$A$4:$A$9,0)),0) -> 0 | R104: =IF(N104="Settled",0,Q104+P104*0.5+IFERROR(INDEX(Config!$B$4:$B$7,MATCH(D104,Config!$A$4:$A$7,0)),1)+IF(C104-Config!$B$1<=1,5,0)) -> 251.5 | S104: =IF(R104=0,"Green",IF(R104<10,"Amber","Red")) -> Red | T104: =IF(N104="Settled","None",IF(C104-Config!$B$1<=0,"Overdue",IF(C104-Config!$B$1<=1,"Critical",IF(C104-Config!$B$1<=3,"High","Low")))) -> Overdue | U104: =IF(R104=0,"",RANK(R104,$R$5:$R$104,0)) -> 8

Sheet Config
A1: Reference Date | B1: =TODAY() -> 46181
A3: Asset Class | B3: Risk Weight
A4: Equity | B4: 1
A5: Fixed Income | B5: 1.5
A6: Derivatives | B6: 2
A7: Commodities | B7: 2.5

Sheet Stage Reference Guide
A1: TRADE LIFECYCLE — STAGE REFERENCE GUIDE
A3: Stage | B3: Stage Name | C3: Description | D3: Operational Purpose | E3: Responsible Team | F3: Systems Used | G3: Failure Points | H3: STP Check
A4: S0 | B4: Trade Capture | C4: Trade details entered / auto-booked into OMS; Trade ID generated | D4: Ensure all execution data is captured accurately in front-office systems | E4: Front Office / Trade Support | F4: Bloomberg AIM, Charles River, FlexTrade | G4: Duplicate booking, wrong quantity, wrong account, missing trade time | H4: STP from execution feed via FIX
A5: S1 | B5: Validation | C5: System validates ISIN, LEI, SSI, counterparty static data | D5: Prevent invalid or stale reference data from progressing through lifecycle | E5: Middle Office / Data Management | F5: Bloomberg Reference Data, In-house Security Master | G5: Invalid ISIN, missing LEI, stale SSI, unknown counterparty | H5: Auto-reject on validation failure
A6: S2 | B6: Enrichment | C6: Trade enriched with settlement details, custodian SSI, accrued interest (FI) | D6: Add all settlement-critical data required for downstream processing | E6: Middle Office / Settlement | F6: Static Data Systems, Broadridge, In-house Middleware | G6: Missing SSI, unknown custodian, enrichment timeout, incorrect accrued interest | H6: Auto-enrichment if SSI found in master
A7: S3 | B7: Confirmation | C7: Trade confirmation sent to counterparty; affirmation requested | D7: Establish bilateral agreement on trade economics before matching | E7: Middle Office / Confirmations | F7: Omgeo CTM, Markit Wire, SWIFT MT300 | G7: Late confirmation, unconfirmed trade, wrong counterparty contact | H7: Auto-confirm if electronic matching enabled
A8: S4 | B8: Allocation | C8: Block trade split across funds/accounts; allocation confirmed to prime broker | D8: Ensure correct fund/account attribution for NAV and regulatory reporting | E8: Middle Office / Allocations | F8: OMS, SWIFT MT515, Omgeo CTM | G8: Late allocation, allocation sum ≠ block qty, wrong fund code | H8: Auto-allocate if rules configured in OMS
A9: S5 | B9: Matching | C9: Both counterparties compare and affirm trade details on CTM/DTCC | D9: Achieve affirmed status required for clearing eligibility | E9: Middle Office / Matching | F9: Omgeo CTM, Markit Wire, DTCC TradeSuite | G9: Price/qty mismatch, late affirmation, wrong side, unmatched after cut-off | H9: Auto-match if all details align exactly
A10: S6 | B10: Settlement Instruction | C10: CCP novates; net obligations calculated; initial margin posted | D10: Prepare final settlement instructions for depository/RTGS transmission | E10: Back Office / Clearing | F10: NSCCL, CCIL, DTCC, LCH, SWIFT MT540-543 | G10: Margin shortfall, CCP rejection, netting failure, wrong instruction type | H10: Auto-clear on CCP acceptance
A11: S7 | B11: Settlement | C11: DVP exchange of cash & securities via depository / RTGS | D11: Final exchange of assets; trade completes lifecycle | E11: Back Office / Settlement | F11: NSDL, CDSL, RTGS, SWIFT MT541/543 | G11: Short delivery, funding failure, depot mismatch, late DVP | H11: STP via SWIFT if SSI and cash position correct

Sheet Failure Reference
A1: OPERATIONAL FAILURE SCENARIOS — BREAK MANAGEMENT REFERENCE
A3: Failure Type | B3: Description | C3: Severity Score | D3: Resolution Steps | E3: Risk Level
A4: Matching Break | B4: Price or quantity mismatch between counterparties on affirmation platform; trade remains unmatched | C4: 8 | D4: 1. Identify discrepancy on CTM 2. Call broker middle office 3. Agree correct economics 4. Amend and re-submit affirmation | E4: HIGH
A5: Settlement Fail | B5: DVP fails on settlement date due to insufficient securities or cash at custodian | C5: 10 | D5: 1. Contact CP treasury/custodian immediately 2. Assess short extension possibility 3. Move to fail status if unresolved 4. Calculate interest claim and notify client | E5: CRITICAL
A6: Allocation Error | B6: Block trade allocation sum does not equal block quantity or wrong fund attribution | C6: 7 | D6: 1. Pull original block from OMS 2. Verify allocation percentages 3. Re-allocate correctly 4. Re-submit to prime broker | E6: HIGH
A7: SSI Error | B7: Settlement Standing Instruction missing or incorrect for counterparty/currency/depository | C7: 6 | D7: 1. Contact broker for correct SSI 2. Load SSI into static data 3. Re-run enrichment 4. Escalate if settlement date approaching | E7: MEDIUM
A8: Trade Capture Error | B8: Wrong instrument, quantity, price, or direction captured at booking stage | C8: 5 | D8: 1. Identify error via validation rules 2. Cancel incorrect trade 3. Re-book with correct details 4. Notify trader and compliance | E8: MEDIUM
A9: Corporate Action Impact | B9: Stock split, bonus, or rights issue creates position reconciliation break post-settlement | C9: 4 | D9: 1. Pull corporate action record from depository 2. Manually adjust OMS position 3. Pass journal entry 4. Update recon system (TLM/Intellimatch) | E9: LOW

Sheet Broker Scorecard
A1: BROKER PERFORMANCE SCORECARD
A2: Metrics derived from Trade Database | Rolling T+1 Settlement Analysis
A4: Rank | B4: Broker | C4: Total Trades | D4: Settled Trades | E4: Open Breaks | F4: Break Rate % | G4: Avg Aging (Days) | H4: Settlement Success % | I4: STP Rate % | J4: Performance Score
A5: =RANK(J5,$J$5:$J$14,0) -> 2 | B5: HDFC Securities | C5: =COUNTIF('Trade Database'!$K$5:$K$104,B5) -> 11 | D5: =COUNTIFS('Trade Database'!$K$5:$K$104,B5,'Trade Database'!$N$5:$N$104,"Settled") -> 9 | E5: =COUNTIFS('Trade Database'!$K$5:$K$104,B5,'Trade Database'!$N$5:$N$104,"Break") -> 0 | F5: =IF(C5=0,0,E5/C5) -> 0 | G5: =AVERAGEIFS('Trade Database'!$P$5:$P$104,'Trade Database'!$K$5:$K$104,B5,'Trade Database'!$N$5:$N$104,"<>Settled") -> 441 | H5: =IF(C5=0,0,D5/C5) -> 0.81818182 | I5: =IF(C5=0,0,D5/C5) -> 0.81818182 | J5: =H5*0.5+I5*0.3+(1-F5)*0.2 -> 0.85454545
A6: =RANK(J6,$J$5:$J$14,0) -> 1 | B6: ICICI Securities | C6: =COUNTIF('Trade Database'!$K$5:$K$104,B6) -> 12 | D6: =COUNTIFS('Trade Database'!$K$5:$K$104,B6,'Trade Database'!$N$5:$N$104,"Settled") -> 11 | E6: =COUNTIFS('Trade Database'!$K$5:$K$104,B6,'Trade Database'!$N$5:$N$104,"Break") -> 0 | F6: =IF(C6=0,0,E6/C6) -> 0 | G6: =AVERAGEIFS('Trade Database'!$P$5:$P$104,'Trade Database'!$K$5:$K$104,B6,'Trade Database'!$N$5:$N$104,"<>Settled") -> 383 | H6: =IF(C6=0,0,D6/C6) -> 0.91666667 | I6: =IF(C6=0,0,D6/C6) -> 0.91666667 | J6: =H6*0.5+I6*0.3+(1-F6)*0.2 -> 0.93333333
A7: =RANK(J7,$J$5:$J$14,0) -> 10 | B7: Motilal Oswal | C7: =COUNTIF('Trade Database'!$K$5:$K$104,B7) -> 7 | D7: =COUNTIFS('Trade Database'!$K$5:$K$104,B7,'Trade Database'!$N$5:$N$104,"Settled") -> 3 | E7: =COUNTIFS('Trade Database'!$K$5:$K$104,B7,'Trade Database'!$N$5:$N$104,"Break") -> 1 | F7: =IF(C7=0,0,E7/C7) -> 0.14285714 | G7: =AVERAGEIFS('Trade Database'!$P$5:$P$104,'Trade Database'!$K$5:$K$104,B7,'Trade Database'!$N$5:$N$104,"<>Settled") -> 472.75 | H7: =IF(C7=0,0,D7/C7) -> 0.42857143 | I7: =IF(C7=0,0,D7/C7) -> 0.42857143 | J7: =H7*0.5+I7*0.3+(1-F7)*0.2 -> 0.51428571
A8: =RANK(J8,$J$5:$J$14,0) -> 3 | B8: Kotak Securities | C8: =COUNTIF('Trade Database'!$K$5:$K$104,B8) -> 10 | D8: =COUNTIFS('Trade Database'!$K$5:$K$104,B8,'Trade Database'!$N$5:$N$104,"Settled") -> 8 | E8: =COUNTIFS('Trade Database'!$K$5:$K$104,B8,'Trade Database'!$N$5:$N$104,"Break") -> 1 | F8: =IF(C8=0,0,E8/C8) -> 0.1 | G8: =AVERAGEIFS('Trade Database'!$P$5:$P$104,'Trade Database'!$K$5:$K$104,B8,'Trade Database'!$N$5:$N$104,"<>Settled") -> 473.5 | H8: =IF(C8=0,0,D8/C8) -> 0.8 | I8: =IF(C8=0,0,D8/C8) -> 0.8 | J8: =H8*0.5+I8*0.3+(1-F8)*0.2 -> 0.82
A9: =RANK(J9,$J$5:$J$14,0) -> 6 | B9: Axis Securities | C9: =COUNTIF('Trade Database'!$K$5:$K$104,B9) -> 8 | D9: =COUNTIFS('Trade Database'!$K$5:$K$104,B9,'Trade Database'!$N$5:$N$104,"Settled") -> 6 | E9: =COUNTIFS('Trade Database'!$K$5:$K$104,B9,'Trade Database'!$N$5:$N$104,"Break") -> 1 | F9: =IF(C9=0,0,E9/C9) -> 0.125 | G9: =AVERAGEIFS('Trade Database'!$P$5:$P$104,'Trade Database'!$K$5:$K$104,B9,'Trade Database'!$N$5:$N$104,"<>Settled") -> 418 | H9: =IF(C9=0,0,D9/C9) -> 0.75 | I9: =IF(C9=0,0,D9/C9) -> 0.75 | J9: =H9*0.5+I9*0.3+(1-F9)*0.2 -> 0.775
A10: =RANK(J10,$J$5:$J$14,0) -> 6 | B10: Sharekhan | C10: =COUNTIF('Trade Database'!$K$5:$K$104,B10) -> 8 | D10: =COUNTIFS('Trade Database'!$K$5:$K$104,B10,'Trade Database'!$N$5:$N$104,"Settled") -> 6 | E10: =COUNTIFS('Trade Database'!$K$5:$K$104,B10,'Trade Database'!$N$5:$N$104,"Break") -> 1 | F10: =IF(C10=0,0,E10/C10) -> 0.125 | G10: =AVERAGEIFS('Trade Database'!$P$5:$P$104,'Trade Database'!$K$5:$K$104,B10,'Trade Database'!$N$5:$N$104,"<>Settled") -> 499 | H10: =IF(C10=0,0,D10/C10) -> 0.75 | I10: =IF(C10=0,0,D10/C10) -> 0.75 | J10: =H10*0.5+I10*0.3+(1-F10)*0.2 -> 0.775
A11: =RANK(J11,$J$5:$J$14,0) -> 5 | B11: Angel One | C11: =COUNTIF('Trade Database'!$K$5:$K$104,B11) -> 12 | D11: =COUNTIFS('Trade Database'!$K$5:$K$104,B11,'Trade Database'!$N$5:$N$104,"Settled") -> 9 | E11: =COUNTIFS('Trade Database'!$K$5:$K$104,B11,'Trade Database'!$N$5:$N$104,"Break") -> 1 | F11: =IF(C11=0,0,E11/C11) -> 0.083333333 | G11: =AVERAGEIFS('Trade Database'!$P$5:$P$104,'Trade Database'!$K$5:$K$104,B11,'Trade Database'!$N$5:$N$104,"<>Settled") -> 439.33333 | H11: =IF(C11=0,0,D11/C11) -> 0.75 | I11: =IF(C11=0,0,D11/C11) -> 0.75 | J11: =H11*0.5+I11*0.3+(1-F11)*0.2 -> 0.78333333
A12: =RANK(J12,$J$5:$J$14,0) -> 4 | B12: IIFL Securities | C12: =COUNTIF('Trade Database'!$K$5:$K$104,B12) -> 11 | D12: =COUNTIFS('Trade Database'!$K$5:$K$104,B12,'Trade Database'!$N$5:$N$104,"Settled") -> 9 | E12: =COUNTIFS('Trade Database'!$K$5:$K$104,B12,'Trade Database'!$N$5:$N$104,"Break") -> 2 | F12: =IF(C12=0,0,E12/C12) -> 0.18181818 | G12: =AVERAGEIFS('Trade Database'!$P$5:$P$104,'Trade Database'!$K$5:$K$104,B12,'Trade Database'!$N$5:$N$104,"<>Settled") -> 457.5 | H12: =IF(C12=0,0,D12/C12) -> 0.81818182 | I12: =IF(C12=0,0,D12/C12) -> 0.81818182 | J12: =H12*0.5+I12*0.3+(1-F12)*0.2 -> 0.81818182
A13: =RANK(J13,$J$5:$J$14,0) -> 9 | B13: JM Financial | C13: =COUNTIF('Trade Database'!$K$5:$K$104,B13) -> 10 | D13: =COUNTIFS('Trade Database'!$K$5:$K$104,B13,'Trade Database'!$N$5:$N$104,"Settled") -> 6 | E13: =COUNTIFS('Trade Database'!$K$5:$K$104,B13,'Trade Database'!$N$5:$N$104,"Break") -> 1 | F13: =IF(C13=0,0,E13/C13) -> 0.1 | G13: =AVERAGEIFS('Trade Database'!$P$5:$P$104,'Trade Database'!$K$5:$K$104,B13,'Trade Database'!$N$5:$N$104,"<>Settled") -> 434.75 | H13: =IF(C13=0,0,D13/C13) -> 0.6 | I13: =IF(C13=0,0,D13/C13) -> 0.6 | J13: =H13*0.5+I13*0.3+(1-F13)*0.2 -> 0.66
A14: =RANK(J14,$J$5:$J$14,0) -> 8 | B14: Nuvama Wealth | C14: =COUNTIF('Trade Database'!$K$5:$K$104,B14) -> 11 | D14: =COUNTIFS('Trade Database'!$K$5:$K$104,B14,'Trade Database'!$N$5:$N$104,"Settled") -> 8 | E14: =COUNTIFS('Trade Database'!$K$5:$K$104,B14,'Trade Database'!$N$5:$N$104,"Break") -> 2 | F14: =IF(C14=0,0,E14/C14) -> 0.18181818 | G14: =AVERAGEIFS('Trade Database'!$P$5:$P$104,'Trade Database'!$K$5:$K$104,B14,'Trade Database'!$N$5:$N$104,"<>Settled") -> 436 | H14: =IF(C14=0,0,D14/C14) -> 0.72727273 | I14: =IF(C14=0,0,D14/C14) -> 0.72727273 | J14: =H14*0.5+I14*0.3+(1-F14)*0.2 -> 0.74545455

Sheet Break Management Center
A1: BREAK MANAGEMENT CENTER
A2: Real-time break analysis by dimension | Heatmap intensity = break concentration
A4: BREAKS BY BROKER | G4: BREAKS BY ASSET CLASS
A5: Broker | B5: Break Count | C5: Total Value (₹) | D5: Avg Severity | G5: Asset Class | H5: Break Count | I5: Total Value (₹) | J5: Avg Severity
A6: HDFC Securities | B6: =COUNTIFS('Trade Database'!$K$5:$K$104,A6,'Trade Database'!$N$5:$N$104,"Break") -> 0 | C6: =SUMIFS('Trade Database'!$J$5:$J$104,'Trade Database'!$K$5:$K$104,A6,'Trade Database'!$N$5:$N$104,"Break") -> 0 | D6: =IFERROR(AVERAGEIFS('Trade Database'!$Q$5:$Q$104,'Trade Database'!$K$5:$K$104,A6,'Trade Database'!$N$5:$N$104,"Break"),0) -> 0 | G6: Equity | H6: =COUNTIFS('Trade Database'!$D$5:$D$104,G6,'Trade Database'!$N$5:$N$104,"Break") -> 4 | I6: =SUMIFS('Trade Database'!$J$5:$J$104,'Trade Database'!$D$5:$D$104,G6,'Trade Database'!$N$5:$N$104,"Break") -> 5453831 | J6: =IFERROR(AVERAGEIFS('Trade Database'!$Q$5:$Q$104,'Trade Database'!$D$5:$D$104,G6,'Trade Database'!$N$5:$N$104,"Break"),0) -> 7
A7: ICICI Securities | B7: =COUNTIFS('Trade Database'!$K$5:$K$104,A7,'Trade Database'!$N$5:$N$104,"Break") -> 0 | C7: =SUMIFS('Trade Database'!$J$5:$J$104,'Trade Database'!$K$5:$K$104,A7,'Trade Database'!$N$5:$N$104,"Break") -> 0 | D7: =IFERROR(AVERAGEIFS('Trade Database'!$Q$5:$Q$104,'Trade Database'!$K$5:$K$104,A7,'Trade Database'!$N$5:$N$104,"Break"),0) -> 0 | G7: Fixed Income | H7: =COUNTIFS('Trade Database'!$D$5:$D$104,G7,'Trade Database'!$N$5:$N$104,"Break") -> 3 | I7: =SUMIFS('Trade Database'!$J$5:$J$104,'Trade Database'!$D$5:$D$104,G7,'Trade Database'!$N$5:$N$104,"Break") -> 2502850 | J7: =IFERROR(AVERAGEIFS('Trade Database'!$Q$5:$Q$104,'Trade Database'!$D$5:$D$104,G7,'Trade Database'!$N$5:$N$104,"Break"),0) -> 6.3333333
A8: Motilal Oswal | B8: =COUNTIFS('Trade Database'!$K$5:$K$104,A8,'Trade Database'!$N$5:$N$104,"Break") -> 1 | C8: =SUMIFS('Trade Database'!$J$5:$J$104,'Trade Database'!$K$5:$K$104,A8,'Trade Database'!$N$5:$N$104,"Break") -> 2891.53 | D8: =IFERROR(AVERAGEIFS('Trade Database'!$Q$5:$Q$104,'Trade Database'!$K$5:$K$104,A8,'Trade Database'!$N$5:$N$104,"Break"),0) -> 10 | G8: Derivatives | H8: =COUNTIFS('Trade Database'!$D$5:$D$104,G8,'Trade Database'!$N$5:$N$104,"Break") -> 2 | I8: =SUMIFS('Trade Database'!$J$5:$J$104,'Trade Database'!$D$5:$D$104,G8,'Trade Database'!$N$5:$N$104,"Break") -> 3071.91 | J8: =IFERROR(AVERAGEIFS('Trade Database'!$Q$5:$Q$104,'Trade Database'!$D$5:$D$104,G8,'Trade Database'!$N$5:$N$104,"Break"),0) -> 8
A9: Kotak Securities | B9: =COUNTIFS('Trade Database'!$K$5:$K$104,A9,'Trade Database'!$N$5:$N$104,"Break") -> 1 | C9: =SUMIFS('Trade Database'!$J$5:$J$104,'Trade Database'!$K$5:$K$104,A9,'Trade Database'!$N$5:$N$104,"Break") -> 497550 | D9: =IFERROR(AVERAGEIFS('Trade Database'!$Q$5:$Q$104,'Trade Database'!$K$5:$K$104,A9,'Trade Database'!$N$5:$N$104,"Break"),0) -> 8 | G9: Commodities | H9: =COUNTIFS('Trade Database'!$D$5:$D$104,G9,'Trade Database'!$N$5:$N$104,"Break") -> 1 | I9: =SUMIFS('Trade Database'!$J$5:$J$104,'Trade Database'!$D$5:$D$104,G9,'Trade Database'!$N$5:$N$104,"Break") -> 68.25 | J9: =IFERROR(AVERAGEIFS('Trade Database'!$Q$5:$Q$104,'Trade Database'!$D$5:$D$104,G9,'Trade Database'!$N$5:$N$104,"Break"),0) -> 10
A10: Axis Securities | B10: =COUNTIFS('Trade Database'!$K$5:$K$104,A10,'Trade Database'!$N$5:$N$104,"Break") -> 1 | C10: =SUMIFS('Trade Database'!$J$5:$J$104,'Trade Database'!$K$5:$K$104,A10,'Trade Database'!$N$5:$N$104,"Break") -> 180.38 | D10: =IFERROR(AVERAGEIFS('Trade Database'!$Q$5:$Q$104,'Trade Database'!$K$5:$K$104,A10,'Trade Database'!$N$5:$N$104,"Break"),0) -> 6
A11: Sharekhan | B11: =COUNTIFS('Trade Database'!$K$5:$K$104,A11,'Trade Database'!$N$5:$N$104,"Break") -> 1 | C11: =SUMIFS('Trade Database'!$J$5:$J$104,'Trade Database'!$K$5:$K$104,A11,'Trade Database'!$N$5:$N$104,"Break") -> 68.25 | D11: =IFERROR(AVERAGEIFS('Trade Database'!$Q$5:$Q$104,'Trade Database'!$K$5:$K$104,A11,'Trade Database'!$N$5:$N$104,"Break"),0) -> 10
A12: BREAKS BY FAILURE TYPE | B12: =COUNTIFS('Trade Database'!$K$5:$K$104,A12,'Trade Database'!$N$5:$N$104,"Break") -> 0 | C12: =SUMIFS('Trade Database'!$J$5:$J$104,'Trade Database'!$K$5:$K$104,A12,'Trade Database'!$N$5:$N$104,"Break") -> 0 | D12: =IFERROR(AVERAGEIFS('Trade Database'!$Q$5:$Q$104,'Trade Database'!$K$5:$K$104,A12,'Trade Database'!$N$5:$N$104,"Break"),0) -> 0 | G12: BREAKS BY MONTH
A13: Failure Type | B13: Count | C13: Total Value (₹) | D13: % of Breaks | G13: Month | H13: Break Count | I13: Total Trades | J13: Break Rate %
A14: Matching Break | B14: =COUNTIF('Trade Database'!$O$5:$O$104,A14) -> 3 | C14: =SUMIF('Trade Database'!$O$5:$O$104,A14,'Trade Database'!$J$5:$J$104) -> 1728901 | D14: =IF($B$20=0,0,B14/$B$20) -> 0.3 | G14: Jan-2025 | H14: =SUMPRODUCT((TEXT('Trade Database'!$B$5:$B$104,"MMM-YYYY")=G14)*('Trade Database'!$N$5:$N$104="Break")) -> 4 | I14: =SUMPRODUCT((TEXT('Trade Database'!$B$5:$B$104,"MMM-YYYY")=G14)*1) -> 15 | J14: =IF(I14=0,0,H14/I14) -> 0.26666667
A15: Settlement Fail | B15: =COUNTIF('Trade Database'!$O$5:$O$104,A15) -> 2 | C15: =SUMIF('Trade Database'!$O$5:$O$104,A15,'Trade Database'!$J$5:$J$104) -> 2959.78 | D15: =IF($B$20=0,0,B15/$B$20) -> 0.2 | G15: Feb-2025 | H15: =SUMPRODUCT((TEXT('Trade Database'!$B$5:$B$104,"MMM-YYYY")=G15)*('Trade Database'!$N$5:$N$104="Break")) -> 1 | I15: =SUMPRODUCT((TEXT('Trade Database'!$B$5:$B$104,"MMM-YYYY")=G15)*1) -> 20 | J15: =IF(I15=0,0,H15/I15) -> 0.05
A16: Allocation Error | B16: =COUNTIF('Trade Database'!$O$5:$O$104,A16) -> 2 | C16: =SUMIF('Trade Database'!$O$5:$O$104,A16,'Trade Database'!$J$5:$J$104) -> 1786060 | D16: =IF($B$20=0,0,B16/$B$20) -> 0.2 | G16: Mar-2025 | H16: =SUMPRODUCT((TEXT('Trade Database'!$B$5:$B$104,"MMM-YYYY")=G16)*('Trade Database'!$N$5:$N$104="Break")) -> 2 | I16: =SUMPRODUCT((TEXT('Trade Database'!$B$5:$B$104,"MMM-YYYY")=G16)*1) -> 16 | J16: =IF(I16=0,0,H16/I16) -> 0.125
A17: SSI Error | B17: =COUNTIF('Trade Database'!$O$5:$O$104,A17) -> 1 | C17: =SUMIF('Trade Database'!$O$5:$O$104,A17,'Trade Database'!$J$5:$J$104) -> 180.38 | D17: =IF($B$20=0,0,B17/$B$20) -> 0.1 | G17: Apr-2025 | H17: =SUMPRODUCT((TEXT('Trade Database'!$B$5:$B$104,"MMM-YYYY")=G17)*('Trade Database'!$N$5:$N$104="Break")) -> 2 | I17: =SUMPRODUCT((TEXT('Trade Database'!$B$5:$B$104,"MMM-YYYY")=G17)*1) -> 18 | J17: =IF(I17=0,0,H17/I17) -> 0.11111111
A18: Trade Capture Error | B18: =COUNTIF('Trade Database'!$O$5:$O$104,A18) -> 1 | C18: =SUMIF('Trade Database'!$O$5:$O$104,A18,'Trade Database'!$J$5:$J$104) -> 3432720 | D18: =IF($B$20=0,0,B18/$B$20) -> 0.1 | G18: May-2025 | H18: =SUMPRODUCT((TEXT('Trade Database'!$B$5:$B$104,"MMM-YYYY")=G18)*('Trade Database'!$N$5:$N$104="Break")) -> 1 | I18: =SUMPRODUCT((TEXT('Trade Database'!$B$5:$B$104,"MMM-YYYY")=G18)*1) -> 14 | J18: =IF(I18=0,0,H18/I18) -> 0.071428571
A19: Corporate Action Impact | B19: =COUNTIF('Trade Database'!$O$5:$O$104,A19) -> 1 | C19: =SUMIF('Trade Database'!$O$5:$O$104,A19,'Trade Database'!$J$5:$J$104) -> 1009000 | D19: =IF($B$20=0,0,B19/$B$20) -> 0.1 | G19: Jun-2025 | H19: =SUMPRODUCT((TEXT('Trade Database'!$B$5:$B$104,"MMM-YYYY")=G19)*('Trade Database'!$N$5:$N$104="Break")) -> 0 | I19: =SUMPRODUCT((TEXT('Trade Database'!$B$5:$B$104,"MMM-YYYY")=G19)*1) -> 17 | J19: =IF(I19=0,0,H19/I19) -> 0
A20: TOTAL | B20: =SUM(B14:B19) -> 10 | C20: =SUM(C14:C19) -> 7959821.2 | D20: =SUM(D14:D19) -> 1

Sheet SLA Monitoring Center
A1: SLA MONITORING CENTER
A2: T+1 Settlement SLA Tracking | Green = Within SLA | Amber = Near Breach | Red = Breached
A4: SLA DEFINITIONS | G4: SLA METRICS
A5: Stage | B5: SLA Target | C5: Within SLA | D5: Near Breach | E5: Breached | G5: Metric | H5: Count | I5: Percentage | J5: Status
A6: S0 Trade Capture | B6: T+15 min | C6: Aging ≤ 0.5 days | D6: Aging 0.5-1 day | E6: Aging > 1 day | G6: Within SLA | H6: =COUNTIFS('Trade Database'!$N$5:$N$104,"Settled")+COUNTIFS('Trade Database'!$N$5:$N$104,"In Progress",'Trade Database'!$P$5:$P$104,"<=1") -> 75 | I6: =H6/100 -> 0.75 | J6: =IF(I6>=0.8,"GOOD","REVIEW") -> REVIEW
A7: S1 Validation | B7: T+30 min | C7: Aging ≤ 0.5 days | D7: Aging 0.5-1 day | E7: Aging > 1 day | G7: Near Breach | H7: =COUNTIFS('Trade Database'!$N$5:$N$104,"In Progress",'Trade Database'!$P$5:$P$104,">1",'Trade Database'!$P$5:$P$104,"<=2") -> 0 | I7: =H7/100 -> 0 | J7: =IF(I7<=0.15,"ACCEPTABLE","ELEVATED") -> ACCEPTABLE
A8: S2 Enrichment | B8: T+2 hours | C8: Aging ≤ 0.5 days | D8: Aging 0.5-1 day | E8: Aging > 1 day | G8: Breached | H8: =COUNTIFS('Trade Database'!$N$5:$N$104,"Break")+COUNTIFS('Trade Database'!$N$5:$N$104,"In Progress",'Trade Database'!$P$5:$P$104,">2") -> 25 | I8: =H8/100 -> 0.25 | J8: =IF(I8<=0.05,"GOOD","CRITICAL") -> CRITICAL
A9: S3 Confirmation | B9: T+4 hours | C9: Aging ≤ 0.5 days | D9: Aging 0.5-1 day | E9: Aging > 1 day | G9: Total Monitored | H9: =SUM(H6:H8) -> 100 | I9: =SUM(I6:I8) -> 1
A10: S4 Allocation | B10: T+6 hours | C10: Aging ≤ 0.5 days | D10: Aging 0.5-1 day | E10: Aging > 1 day
A11: S5 Matching | B11: End of Day T | C11: Aging ≤ 0.5 days | D11: Aging 0.5-1 day | E11: Aging > 1 day
A12: SLA STATUS BY LIFECYCLE STAGE | B12: T+1 09:00 | C12: Aging ≤ 1 day | D12: Aging 1-2 days | E12: Aging > 2 days
A13: Stage | B13: Total | C13: Within SLA | D13: Near Breach | E13: Breached
A14: S0 Trade Capture | B14: =COUNTIF('Trade Database'!$M$5:$M$104,A14) -> 5 | C14: =COUNTIFS('Trade Database'!$M$5:$M$104,A14,'Trade Database'!$P$5:$P$104,"<=1") -> 0 | D14: =COUNTIFS('Trade Database'!$M$5:$M$104,A14,'Trade Database'!$P$5:$P$104,">1",'Trade Database'!$P$5:$P$104,"<=2") -> 0 | E14: =COUNTIFS('Trade Database'!$M$5:$M$104,A14,'Trade Database'!$P$5:$P$104,">2") -> 5
A15: S1 Validation | B15: =COUNTIF('Trade Database'!$M$5:$M$104,A15) -> 3 | C15: =COUNTIFS('Trade Database'!$M$5:$M$104,A15,'Trade Database'!$P$5:$P$104,"<=1") -> 0 | D15: =COUNTIFS('Trade Database'!$M$5:$M$104,A15,'Trade Database'!$P$5:$P$104,">1",'Trade Database'!$P$5:$P$104,"<=2") -> 0 | E15: =COUNTIFS('Trade Database'!$M$5:$M$104,A15,'Trade Database'!$P$5:$P$104,">2") -> 3
A16: S2 Enrichment | B16: =COUNTIF('Trade Database'!$M$5:$M$104,A16) -> 2 | C16: =COUNTIFS('Trade Database'!$M$5:$M$104,A16,'Trade Database'!$P$5:$P$104,"<=1") -> 0 | D16: =COUNTIFS('Trade Database'!$M$5:$M$104,A16,'Trade Database'!$P$5:$P$104,">1",'Trade Database'!$P$5:$P$104,"<=2") -> 0 | E16: =COUNTIFS('Trade Database'!$M$5:$M$104,A16,'Trade Database'!$P$5:$P$104,">2") -> 2
A17: S3 Confirmation | B17: =COUNTIF('Trade Database'!$M$5:$M$104,A17) -> 1 | C17: =COUNTIFS('Trade Database'!$M$5:$M$104,A17,'Trade Database'!$P$5:$P$104,"<=1") -> 0 | D17: =COUNTIFS('Trade Database'!$M$5:$M$104,A17,'Trade Database'!$P$5:$P$104,">1",'Trade Database'!$P$5:$P$104,"<=2") -> 0 | E17: =COUNTIFS('Trade Database'!$M$5:$M$104,A17,'Trade Database'!$P$5:$P$104,">2") -> 1
A18: S4 Allocation | B18: =COUNTIF('Trade Database'!$M$5:$M$104,A18) -> 3 | C18: =COUNTIFS('Trade Database'!$M$5:$M$104,A18,'Trade Database'!$P$5:$P$104,"<=1") -> 0 | D18: =COUNTIFS('Trade Database'!$M$5:$M$104,A18,'Trade Database'!$P$5:$P$104,">1",'Trade Database'!$P$5:$P$104,"<=2") -> 0 | E18: =COUNTIFS('Trade Database'!$M$5:$M$104,A18,'Trade Database'!$P$5:$P$104,">2") -> 3
A19: S5 Matching | B19: =COUNTIF('Trade Database'!$M$5:$M$104,A19) -> 8 | C19: =COUNTIFS('Trade Database'!$M$5:$M$104,A19,'Trade Database'!$P$5:$P$104,"<=1") -> 0 | D19: =COUNTIFS('Trade Database'!$M$5:$M$104,A19,'Trade Database'!$P$5:$P$104,">1",'Trade Database'!$P$5:$P$104,"<=2") -> 0 | E19: =COUNTIFS('Trade Database'!$M$5:$M$104,A19,'Trade Database'!$P$5:$P$104,">2") -> 8
A20: S6 Settlement Instruction | B20: =COUNTIF('Trade Database'!$M$5:$M$104,A20) -> 0 | C20: =COUNTIFS('Trade Database'!$M$5:$M$104,A20,'Trade Database'!$P$5:$P$104,"<=1") -> 0 | D20: =COUNTIFS('Trade Database'!$M$5:$M$104,A20,'Trade Database'!$P$5:$P$104,">1",'Trade Database'!$P$5:$P$104,"<=2") -> 0 | E20: =COUNTIFS('Trade Database'!$M$5:$M$104,A20,'Trade Database'!$P$5:$P$104,">2") -> 0
A21: S7 Settlement | B21: =COUNTIF('Trade Database'!$M$5:$M$104,A21) -> 78 | C21: =COUNTIFS('Trade Database'!$M$5:$M$104,A21,'Trade Database'!$P$5:$P$104,"<=1") -> 0 | D21: =COUNTIFS('Trade Database'!$M$5:$M$104,A21,'Trade Database'!$P$5:$P$104,">1",'Trade Database'!$P$5:$P$104,"<=2") -> 0 | E21: =COUNTIFS('Trade Database'!$M$5:$M$104,A21,'Trade Database'!$P$5:$P$104,">2") -> 78

Sheet Executive Dashboard
A1: EXECUTIVE DASHBOARD
A2: Operations Command Center | Real-time Trade Lifecycle Analytics | L2: =Config!$B$1 -> 46181
A4: Total Trades | F4: Settled Trades | K4: Pending Trades | P4: Asset Class | Q4: Count | S4: Broker | T4: Count | V4: Failure Type | W4: Count | Y4: Month | Z4: Total | AA4: Settled | AC4: Month | AD4: Success %
A5: =COUNTA('Trade Database'!$A$5:$A$104) -> 100 | F5: =COUNTIF('Trade Database'!$N$5:$N$104,"Settled") -> 75 | K5: =COUNTIFS('Trade Database'!$N$5:$N$104,"<>Settled",'Trade Database'!$N$5:$N$104,"<>Break") -> 15 | P5: Equity | Q5: =COUNTIF('Trade Database'!$D$5:$D$104,P5) -> 40 | S5: HDFC Securities | T5: =COUNTIF('Trade Database'!$K$5:$K$104,S5) -> 11 | V5: Matching Break | W5: =COUNTIF('Trade Database'!$O$5:$O$104,V5) -> 3 | Y5: Jan | Z5: =SUMPRODUCT((MONTH('Trade Database'!$B$5:$B$104)=1)*1) -> 15 | AA5: =SUMPRODUCT((MONTH('Trade Database'!$B$5:$B$104)=1)*('Trade Database'!$N$5:$N$104="Settled")) -> 9 | AC5: Jan | AD5: =IF(AG5=0,0,AH5/AG5) -> 0
P6: Fixed Income | Q6: =COUNTIF('Trade Database'!$D$5:$D$104,P6) -> 25 | S6: ICICI Securities | T6: =COUNTIF('Trade Database'!$K$5:$K$104,S6) -> 12 | V6: Settlement Fail | W6: =COUNTIF('Trade Database'!$O$5:$O$104,V6) -> 2 | Y6: Feb | Z6: =SUMPRODUCT((MONTH('Trade Database'!$B$5:$B$104)=2)*1) -> 20 | AA6: =SUMPRODUCT((MONTH('Trade Database'!$B$5:$B$104)=2)*('Trade Database'!$N$5:$N$104="Settled")) -> 15 | AC6: Feb | AD6: =IF(AG6=0,0,AH6/AG6) -> 0
P7: Derivatives | Q7: =COUNTIF('Trade Database'!$D$5:$D$104,P7) -> 20 | S7: Motilal Oswal | T7: =COUNTIF('Trade Database'!$K$5:$K$104,S7) -> 7 | V7: Allocation Error | W7: =COUNTIF('Trade Database'!$O$5:$O$104,V7) -> 2 | Y7: Mar | Z7: =SUMPRODUCT((MONTH('Trade Database'!$B$5:$B$104)=3)*1) -> 16 | AA7: =SUMPRODUCT((MONTH('Trade Database'!$B$5:$B$104)=3)*('Trade Database'!$N$5:$N$104="Settled")) -> 11 | AC7: Mar | AD7: =IF(AG7=0,0,AH7/AG7) -> 0
P8: Commodities | Q8: =COUNTIF('Trade Database'!$D$5:$D$104,P8) -> 15 | S8: Kotak Securities | T8: =COUNTIF('Trade Database'!$K$5:$K$104,S8) -> 10 | V8: SSI Error | W8: =COUNTIF('Trade Database'!$O$5:$O$104,V8) -> 1 | Y8: Apr | Z8: =SUMPRODUCT((MONTH('Trade Database'!$B$5:$B$104)=4)*1) -> 18 | AA8: =SUMPRODUCT((MONTH('Trade Database'!$B$5:$B$104)=4)*('Trade Database'!$N$5:$N$104="Settled")) -> 14 | AC8: Apr | AD8: =IF(AG8=0,0,AH8/AG8) -> 0
A9: Open Breaks | F9: STP Rate | K9: Settlement Success | S9: Axis Securities | T9: =COUNTIF('Trade Database'!$K$5:$K$104,S9) -> 8 | V9: Trade Capture Error | W9: =COUNTIF('Trade Database'!$O$5:$O$104,V9) -> 1 | Y9: May | Z9: =SUMPRODUCT((MONTH('Trade Database'!$B$5:$B$104)=5)*1) -> 14 | AA9: =SUMPRODUCT((MONTH('Trade Database'!$B$5:$B$104)=5)*('Trade Database'!$N$5:$N$104="Settled")) -> 11 | AC9: May | AD9: =IF(AG9=0,0,AH9/AG9) -> 0
A10: =COUNTIF('Trade Database'!$N$5:$N$104,"Break") -> 10 | F10: =COUNTIF('Trade Database'!$N$5:$N$104,"Settled")/COUNTA('Trade Database'!$A$5:$A$104) -> 0.75 | K10: =COUNTIF('Trade Database'!$N$5:$N$104,"Settled")/COUNTA('Trade Database'!$A$5:$A$104) -> 0.75 | V10: Corporate Action Impact | W10: =COUNTIF('Trade Database'!$O$5:$O$104,V10) -> 1 | Y10: Jun | Z10: =SUMPRODUCT((MONTH('Trade Database'!$B$5:$B$104)=6)*1) -> 17 | AA10: =SUMPRODUCT((MONTH('Trade Database'!$B$5:$B$104)=6)*('Trade Database'!$N$5:$N$104="Settled")) -> 15 | AC10: Jun | AD10: =IF(AG10=0,0,AH10/AG10) -> 0
A14: Avg Aging | F14: High Risk Trades | K14: Ops Health Score
A15: =AVERAGE('Trade Database'!$P$5:$P$104) -> 433.75 | F15: =COUNTIF('Trade Database'!$S$5:$S$104,"Red") -> 25 | K15: =MAX(0,100-COUNTIF('Trade Database'!$N$5:$N$104,"Break")*10-COUNTIF('Trade Database'!$S$5:$S$104,"Red")*5-COUNTIFS('Trade Database'!$T$5:$T$104,"Overdue")*3) -> 0
A19: FILTER PANEL
A20: Broker | C20: Asset Class | E20: Status | G20: Failure Type
A21: [Select Broker] | C21: [Select Asset Class] | E21: [Select Status] | G21: [Select Failure Type]
