Workbook

Sheet Trade Lifecycle Tracker
A1: TRADE LIFECYCLE TRACKER — IronHub Capital Operations
A2: Equities | Fixed Income | Derivatives • Simulated Portfolio — T+1 Settlement Simulation | India Markets
A3: STAGE PIPELINE: T → Execution S-1 → Capture S-2 → Validation S-3 → Enrichment S-4 → Allocation S-5 → Matching S-6 → Clearing S-7 → Settlement
A4: Trade ID | B4: Trade Date | C4: Asset Class | D4: Instrument | E4: ISIN | F4: Buy/Sell | G4: Qty (Our) | H4: Qty (CP) | I4: Price Our (₹) | J4: Price CP (₹) | K4: Gross Value (₹) | L4: Broker / CP | M4: Custodian | N4: Settlement Type | O4: Settlement Date | P4: Trade Time (T) | Q4: Capture Time (S-1) | R4: Match Time (S-5) | S4: Settlement Time (S-7) | T4: Current Stage | U4: Lifecycle Status | V4: Failure Reason
A5: TRD-001 | B5: 03-Apr-2025 | C5: Equity | D5: Reliance Industries Ltd | E5: INE002A01018 | F5: BUY | G5: 500 | H5: 500 | I5: 2850 | J5: 2850 | K5: =G5*I5 -> 1425000 | L5: ICICI Securities | M5: HDFC Custody | N5: Rolling (T+1) | O5: 04-Apr-2025 | P5: 09:15:22 | Q5: 09:17:05 | R5: 09:45:18 | S5: 14:32:10 | T5: S-7 Settlement | U5: Completed – Settled
A6: TRD-002 | B6: 03-Apr-2025 | C6: Equity | D6: Infosys Ltd | E6: INE009A01021 | F6: SELL | G6: 300 | H6: 300 | I6: 1520.5 | J6: 1518 | K6: =G6*I6 -> 456150 | L6: Zerodha | M6: Axis Custody | N6: Rolling (T+1) | O6: 04-Apr-2025 | P6: 09:16:40 | Q6: 09:18:55 | T6: S-5 Matching | U6: Break – Investigation | V6: Price mismatch: Our ₹1520.50 vs CP ₹1518.00 — Break raised on Omegeo CTM
A7: TRD-003 | B7: 03-Apr-2025 | C7: Equity | D7: Wipro Ltd | E7: INE075A01022 | F7: BUY | G7: 400 | H7: 398 | I7: 475.25 | J7: 475.25 | K7: =G7*I7 -> 190100 | L7: Angel Broking | M7: Standard Chartered | N7: Rolling (T+1) | O7: 04-Apr-2025 | P7: 09:22:11 | Q7: 09:24:30 | T7: S-5 Matching | U7: Break – Investigation | V7: Qty mismatch: Our 400 vs CP 398 — partial fill not confirmed by broker
A8: TRD-004 | B8: 03-Apr-2025 | C8: Equity | D8: Asian Paints Ltd | E8: INE021A01999 | F8: SELL | G8: 120 | H8: 120 | I8: 2890 | J8: 2890 | K8: =G8*I8 -> 346800 | L8: Macquarie India | M8: ICICI Custody | N8: Rolling (T+1) | O8: 04-Apr-2025 | P8: 09:28:05 | Q8: 09:31:12 | T8: S-2 Validation | U8: Break – Investigation | V8: Invalid ISIN: INE021A01999 — correct ISIN is INE021A01026; trade failed validation
A9: TRD-005 | B9: 02-Apr-2025 | C9: Equity | D9: HDFC Bank Ltd | E9: INE040A01034 | F9: BUY | G9: 200 | H9: 200 | I9: 1675 | J9: 1675 | K9: =G9*I9 -> 335000 | L9: Edelweiss | M9: Kotak Custody | N9: Rolling (T+1) | O9: 03-Apr-2025 | P9: 10:05:44 | Q9: 10:07:20 | T9: S-3 Enrichment | U9: Break – Investigation | V9: Counterparty SSI not found: SSI-EDL-004 missing in static data; enrichment halted
A10: TRD-006 | B10: 01-Apr-2025 | C10: Equity | D10: Tata Consultancy Services | E10: INE467B01029 | F10: BUY | G10: 150 | H10: 150 | I10: 3920 | J10: 3920 | K10: =G10*I10 -> 588000 | L10: Kotak Securities | M10: Citi Custody | N10: Rolling (T+1) | O10: 02-Apr-2025 | P10: 09:45:00 | Q10: 09:46:55 | R10: 10:02:30 | T10: S-7 Settlement | U10: Break – Investigation | V10: Short delivery: Seller delivered 0 units; NSDL auction process triggered
A11: TRD-007 | B11: 01-Apr-2025 | C11: Equity | D11: Bajaj Finance Ltd | E11: INE296A01024 | F11: BUY | G11: 60 | H11: 60 | I11: 7125 | J11: 7125 | K11: =G11*I11 -> 427500 | L11: CLSA India | M11: JP Morgan | N11: Rolling (T+1) | O11: 02-Apr-2025 | P11: 11:10:22 | Q11: 11:12:08 | R11: 11:28:45 | T11: S-7 Settlement | U11: Break – Investigation | V11: Funding failure: CP flagged insufficient cash at custodian on settlement date; repair initiated
A12: TRD-008 | B12: 03-Apr-2025 | C12: Fixed Income | D12: Govt of India 7.26% 2029 Bond | E12: IN0020210203 | F12: BUY | G12: 100 | H12: 100 | I12: 10250 | J12: 10250 | K12: =G12*I12 -> 1025000 | L12: ICICI Securities | M12: Deutsche Custody | N12: T+1 | O12: 04-Apr-2025 | P12: 09:30:00 | Q12: 09:32:15 | R12: 10:15:00 | T12: S-6 Clearing | U12: In Progress
A13: TRD-009 | B13: 03-Apr-2025 | C13: Fixed Income | D13: SBI Perpetual Bond 8.50% | E13: INE062A08209 | F13: SELL | G13: 50 | H13: 50 | I13: 99500 | J13: 99500 | K13: =G13*I13 -> 4975000 | L13: Nomura India | M13: HSBC Custody | N13: T+1 | O13: 04-Apr-2025 | P13: 09:55:10 | Q13: 09:57:22 | T13: S-4 Allocation | U13: In Progress
A14: TRD-010 | B14: 31-Mar-2025 | C14: Fixed Income | D14: NTPC Ltd NCD 7.15% 2027 | E14: INE733E07BZ2 | F14: BUY | G14: 25 | H14: 25 | I14: 100250 | J14: 100250 | K14: =G14*I14 -> 2506250 | L14: IIFL Securities | M14: Axis Custody | N14: T+1 | O14: 01-Apr-2025 | P14: 10:00:00 | Q14: 10:01:45 | R14: 10:25:30 | S14: 14:10:00 | T14: S-7 Settlement | U14: Completed – Settled
A15: TRD-011 | B15: 03-Apr-2025 | C15: Fixed Income | D15: Power Finance Corp Bond 7.8% | E15: INE134E08JL0 | F15: SELL | G15: 30 | H15: 30 | I15: 101200 | J15: 101200 | K15: =G15*I15 -> 3036000 | L15: Goldman Sachs | M15: Deutsche Custody | N15: T+1 | O15: 04-Apr-2025 | P15: 10:15:00 | Q15: 10:16:30 | R15: 10:40:00 | T15: S-6 Clearing | U15: Ready for Settlement
A16: TRD-012 | B16: 03-Apr-2025 | C16: Derivatives | D16: Nifty 50 Futures Apr-2025 | E16: N/A | F16: SELL | G16: 50 | H16: 50 | I16: 22150 | J16: 22150 | K16: =G16*I16 -> 1107500 | L16: Sharekhan | M16: NSCCL | N16: T+0 (Daily) | O16: 03-Apr-2025 | P16: 09:18:00 | Q16: 09:18:45 | R16: 09:20:00 | S16: 12:30:00 | T16: S-7 Settlement | U16: Completed – Settled
A17: TRD-013 | B17: 03-Apr-2025 | C17: Derivatives | D17: USD/INR Currency Futures | E17: N/A | F17: BUY | G17: 200 | H17: 200 | I17: 83.42 | J17: 83.42 | K17: =G17*I17 -> 16684 | L17: ICICI Securities | M17: CCIL | N17: T+0 (Daily) | O17: 03-Apr-2025 | P17: 09:20:00 | Q17: 09:21:10 | R17: 09:22:30 | S17: 12:45:00 | T17: S-7 Settlement | U17: Completed – Settled
A18: TRD-014 | B18: 02-Apr-2025 | C18: Derivatives | D18: Bank Nifty Put Option 48000 | E18: N/A | F18: BUY | G18: 10 | H18: 10 | I18: 185 | J18: 185 | K18: =G18*I18 -> 1850 | L18: Zerodha | M18: NSCCL | N18: T+0 (Daily) | O18: 02-Apr-2025 | P18: 10:30:00 | Q18: 10:30:55 | R18: 10:31:30 | S18: 14:00:00 | T18: S-7 Settlement | U18: Completed – Settled
A19: TRD-015 | B19: 02-Apr-2025 | C19: Equity | D19: Maruti Suzuki India Ltd | E19: INE585B01010 | F19: SELL | G19: 80 | H19: 80 | I19: 12340 | J19: 12340 | K19: =G19*I19 -> 987200 | L19: SBI Securities | M19: BNY Mellon | N19: Rolling (T+1) | O19: 03-Apr-2025 | P19: 11:05:00 | Q19: 11:06:30 | R19: 11:20:00 | T19: S-5 Matching | U19: Break – Investigation | V19: Recon break: OMS qty 80, custody shows 75 — investigating corporate action impact
A20: TOTALS | G20: =SUM(G5:G19) -> 2275 | H20: =SUM(H5:H19) -> 2273 | K20: =SUM(K5:K19) -> 17424034

Sheet Dashboard
A1: OPERATIONS DASHBOARD — Trade Lifecycle Summary
A2: Live metrics derived from Trade Lifecycle Tracker sheet | IronHub Capital | India Equities, Fixed Income & Derivatives
B4: Total Trades | D4: Total Value (₹) | F4: Settled | H4: Break / Failed | J4: Pending Match | L4: In Progress
B5: =COUNTA('Trade Lifecycle Tracker'!A5:A19) -> 15 | D5: =SUM('Trade Lifecycle Tracker'!K5:K19) -> 17424034 | F5: =COUNTIF('Trade Lifecycle Tracker'!U5:U19,"Completed – Settled") -> 5 | H5: =COUNTIF('Trade Lifecycle Tracker'!U5:U19,"Break – Investigation") -> 7 | J5: =COUNTIF('Trade Lifecycle Tracker'!U5:U19,"Pending Match") -> 0 | L5: =COUNTIF('Trade Lifecycle Tracker'!U5:U19,"In Progress") -> 2
B8: Category | C8: Count | D8: Gross Value (₹) | E8: % of Trades
B9: Equity | C9: =COUNTIF('Trade Lifecycle Tracker'!C5:C19,"Equity") -> 8 | D9: =SUMIF('Trade Lifecycle Tracker'!C5:C19,"Equity",'Trade Lifecycle Tracker'!K5:K19) -> 4755750 | E9: =C9/$C$12 -> 0.53333333
B10: Fixed Income | C10: =COUNTIF('Trade Lifecycle Tracker'!C5:C19,"Fixed Income") -> 4 | D10: =SUMIF('Trade Lifecycle Tracker'!C5:C19,"Fixed Income",'Trade Lifecycle Tracker'!K5:K19) -> 11542250 | E10: =C10/$C$12 -> 0.26666667
B11: Derivatives | C11: =COUNTIF('Trade Lifecycle Tracker'!C5:C19,"Derivatives") -> 3 | D11: =SUMIF('Trade Lifecycle Tracker'!C5:C19,"Derivatives",'Trade Lifecycle Tracker'!K5:K19) -> 1126034 | E11: =C11/$C$12 -> 0.2
B12: TOTAL | C12: =SUM(C9:C11) -> 15 | D12: =SUM(D9:D11) -> 17424034 | E12: =SUM(E9:E11) -> 1
B14: SETTLEMENT STATUS BREAKDOWN
B15: Status | C15: Count | D15: % of Total | E15: Risk Flag
B16: Completed – Settled | C16: =COUNTIF('Trade Lifecycle Tracker'!U5:U19,"Completed – Settled") -> 5 | D16: =C16/B5 -> 0.33333333 | E16: ✔ Clean
B17: In Progress | C17: =COUNTIF('Trade Lifecycle Tracker'!U5:U19,"In Progress") -> 2 | D17: =C17/B5 -> 0.13333333 | E17: ⚠ Monitor
B18: Break – Investigation | C18: =COUNTIF('Trade Lifecycle Tracker'!U5:U19,"Break – Investigation") -> 7 | D18: =C18/B5 -> 0.46666667 | E18: ✖ Urgent
B19: Ready for Settlement | C19: =COUNTIF('Trade Lifecycle Tracker'!U5:U19,"Ready for Settlement") -> 1 | D19: =C19/B5 -> 0.066666667 | E19: → STP
B20: Pending Match | C20: =COUNTIF('Trade Lifecycle Tracker'!U5:U19,"Pending Match") -> 0 | D20: =C20/B5 -> 0 | E20: ⚠ Chase CP

Sheet Stage Reference Guide
A1: TRADE LIFECYCLE — STAGE REFERENCE GUIDE
A2: Stage | B2: Stage Name | C2: Key Activity | D2: Systems Used | E2: Failure Points | F2: STP Check
A3: T | B3: Trade Execution | C3: PM/trader executes order on exchange or OTC; fill confirmed | D3: Exchange engine, DMA, Bloomberg EMSX | E3: Wrong instrument, wrong price, partial fill, latency | F3: Auto-confirm via FIX
A4: S-1 | B4: Trade Capture | C4: Trade details entered / auto-booked into OMS (Trade ID generated) | D4: OMS (Bloomberg AIM, Charles River, Flextrade) | E4: Duplicate booking, wrong quantity, wrong account | F4: STP from execution feed
A5: S-2 | B5: Validation | C5: System validates ISIN, LEI, SSI, counterparty static data | D5: Static data systems, Bloomberg Reference Data | E5: Invalid ISIN, missing LEI, stale SSI, unknown CP | F5: Auto-reject on failure
A6: S-3 | B6: Enrichment | C6: Trade enriched with settlement details, custodian SSI, accrued interest (FI) | D6: Static data, in-house middleware, Broadridge | E6: Missing SSI, unknown custodian, enrichment timeout | F6: Auto-enrichment if SSI found
A7: S-4 | B7: Allocation | C7: Block trade split across funds/accounts; allocation confirmed to prime broker | D7: OMS, SWIFT MT515, Omegeo CTM | E7: Late allocation, allocation sum ≠ block qty | F7: Auto-allocate if rules configured
A8: S-5 | B8: Matching & Affirmation | C8: Both counterparties compare and affirm trade details on CTM/DTCC | D8: Omegeo CTM, Markit Wire, DTCC TradeSuite | E8: Price/qty mismatch, late affirmation, wrong side | F8: Auto-match if details match
A9: S-6 | B9: Clearing | C9: CCP novates; net obligations calculated; initial margin posted | D9: NSCCL, CCIL, DTCC, LCH | E9: Margin shortfall, CCP rejection, netting failure | F9: Auto-clear on CCP acceptance
A10: S-7 | B10: Settlement | C10: DVP exchange of cash & securities via depository / RTGS | D10: NSDL, CDSL, RTGS, SWIFT MT541/543 | E10: Short delivery, funding failure, depot mismatch | F10: STP via SWIFT if SSI correct

Sheet Failure Scenarios
A1: OPERATIONAL FAILURE SCENARIOS — Break Management Reference
A2: Real desk scenarios you must know for IB Operations interviews — each mapped to a lifecycle stage and resolution path
A3: # | B3: Failure Type | C3: Stage | D3: Description | E3: Root Cause | F3: Resolution Steps | G3: Risk Level
A4: 1 | B4: Price Mismatch | C4: S-5 Matching | D4: Our price ₹1520.50 vs CP price ₹1518.00 — trade unmatched on Omegeo CTM | E4: Broker fat-finger or system rounding difference in price feed | F4: 1. Identify discrepancy on CTM 2. Call/email broker middle office 3. Agree correct price 4. Amend and re-submit affirmation | G4: HIGH
A5: 2 | B5: Quantity Mismatch | C5: S-5 Matching | D5: Our qty 400 vs CP qty 398 — partial fill not captured on CP side | E5: Broker sent partial fill confirmation; full block not confirmed | F5: 1. Pull execution report from broker 2. Check FIX drop copy 3. Confirm partial vs full fill 4. Re-allocate if needed | G5: HIGH
A6: 3 | B6: Wrong ISIN | C6: S-2 Validation | D6: ISIN INE021A01999 used — correct ISIN is INE021A01026 (Asian Paints) | E6: Ops keying error or stale security master — static data not updated | F6: 1. Reject trade at validation 2. Correct ISIN in OMS 3. Amend booking 4. Update security master | G6: CRITICAL
A7: 4 | B7: Counterparty / SSI Not Found | C7: S-3 Enrichment | D7: SSI-EDL-004 missing from static data — enrichment halted at S-3 | E7: New broker on-boarded without SSI loaded into settlement system | F7: 1. Contact broker to obtain SSI details 2. Load SSI into static data 3. Re-run enrichment 4. Escalate if settlement date approaching | G7: HIGH
A8: 5 | B8: Short Delivery | C8: S-7 Settlement | D8: Seller delivers 0 units on settlement date — buy-side receives nothing | E8: Seller had insufficient securities in depository account (NSDL/CDSL) | F8: 1. NSDL triggers auction process 2. Claim penalty from defaulting seller 3. Buy-in at auction price 4. Notify client of delay | G8: CRITICAL
A9: 6 | B9: Funding Failure (Cash) | C9: S-7 Settlement | D9: CP's custodian flags insufficient cash — DVP fails on settlement day | E9: CP did not fund their settlement account; treasury oversight failure | F9: 1. Contact CP treasury immediately 2. Agree short extension if possible 3. Move to fail status 4. Calculate interest claim | G9: HIGH
A10: 7 | B10: Late Affirmation | C10: S-5 Matching | D10: Affirmation received after CTM cut-off — ineligible for STP clearing | E10: Buy-side PM did not approve allocation in time; manual intervention required | F10: 1. Force-match with supervisor approval 2. Move to manual clearing track 3. Escalate PM tardiness 4. Review SLA | G10: MEDIUM
A11: 8 | B11: Reconciliation Break — Position | C11: Post-Settlement | D11: OMS shows 80 units Maruti; custody statement shows 75 — 5 unit break | E11: Corporate action (stock split/bonus) not reflected in OMS; custody updated first | F11: 1. Pull corporate action record 2. Manually adjust OMS position 3. Pass journal entry 4. Update recon system (TLM/Intellimatch) | G11: MEDIUM
A12: 9 | B12: Margin Shortfall | C12: S-6 Clearing | D12: CCP rejects clearing due to insufficient initial margin posted for derivative | E12: MTM move overnight increased margin requirement; firm treasury not notified | F12: 1. Urgent margin call to treasury 2. Post additional margin via RTGS 3. Confirm with NSCCL/CCIL 4. Review margin model thresholds | G12: CRITICAL
A13: 10 | B13: SWIFT Instruction Failure | C13: S-7 Settlement | D13: MT541 rejected by custodian — missing mandatory field (LEI of counterparty) | E13: LEI not stored in settlement system for new counterparty | F13: 1. Obtain LEI from GLEIF database 2. Update static data 3. Re-send corrected MT541 4. Confirm custodian acknowledgement | G13: HIGH
